Workbook

Sheet 用例统计
A1: 诚心售2.0 - 测试用例统计 (V2.0)
A3: 优先级定义标准:
A4: P1(阻断级) | B4: 直接资金安全风险/数据不可恢复/核心状态机破坏,阻断核心业务流程。发版前必须100%通过
A5: P2(高优级) | B5: 核心功能验证/状态流转/权限校验/数据隔离等关键业务路径。发版前必须通过
A6: P3(中优级) | B6: 辅助功能验证/筛选搜索/展示交互/分页加载等常规功能。发版前应通过
A7: P4(低优级) | B7: 边缘场景/空状态/审计日志/非核心展示等非关键路径。发版后修复
A8: P5(极低级) | B8: UI微调/文案优化/兼容性边缘等非功能性问题。迭代优化
A10: 优化说明:
A11: 1.本次用例覆盖前台4模块(24条)+后台2模块(16条),共40条,每模块>=5条
A12: 2.P1仅2条(去支付+申请退款,均为资金安全类),占比5.0%<=15%
A13: 3.诚心售2.0核心变化为「独立Tab」,重点覆盖服务列表隔离(双向不可见断言)
A14: 4.资金状态与履约奖励配置模块覆盖并发校验(乐观锁)和配置变更影响
A15: 5.终态订单(已取消/已违约/已成交)合并为1条多断言用例(合并规则)
A16: 6.所有「待确认」项在缺失分析Sheet记录,禁止基于假设补充功能
A17: 7.统计数据使用Excel公式动态计算,非硬编码
A19: 模块 | B19: 用例数 | C19: P1 | D19: P2 | E19: P3 | F19: P4 | G19: P5
A20: 前台-诚心售Tab入口与图标展示 | B20: =COUNTA('前台-诚心售Tab入口与图标展示'!A3:A1000) -> 6 | C20: =COUNTIF('前台-诚心售Tab入口与图标展示'!C3:C1000,"P1") -> 0 | D20: =COUNTIF('前台-诚心售Tab入口与图标展示'!C3:C1000,"P2") -> 2 | E20: =COUNTIF('前台-诚心售Tab入口与图标展示'!C3:C1000,"P3") -> 3 | F20: =COUNTIF('前台-诚心售Tab入口与图标展示'!C3:C1000,"P4") -> 1 | G20: =COUNTIF('前台-诚心售Tab入口与图标展示'!C3:C1000,"P5") -> 0
A21: 前台-诚心售订单列表与状态筛选 | B21: =COUNTA('前台-诚心售订单列表与状态筛选'!A3:A1000) -> 7 | C21: =COUNTIF('前台-诚心售订单列表与状态筛选'!C3:C1000,"P1") -> 0 | D21: =COUNTIF('前台-诚心售订单列表与状态筛选'!C3:C1000,"P2") -> 4 | E21: =COUNTIF('前台-诚心售订单列表与状态筛选'!C3:C1000,"P3") -> 3 | F21: =COUNTIF('前台-诚心售订单列表与状态筛选'!C3:C1000,"P4") -> 0 | G21: =COUNTIF('前台-诚心售订单列表与状态筛选'!C3:C1000,"P5") -> 0
A22: 前台-诚心售订单操作与状态流转 | B22: =COUNTA('前台-诚心售订单操作与状态流转'!A3:A1000) -> 7 | C22: =COUNTIF('前台-诚心售订单操作与状态流转'!C3:C1000,"P1") -> 2 | D22: =COUNTIF('前台-诚心售订单操作与状态流转'!C3:C1000,"P2") -> 4 | E22: =COUNTIF('前台-诚心售订单操作与状态流转'!C3:C1000,"P3") -> 1 | F22: =COUNTIF('前台-诚心售订单操作与状态流转'!C3:C1000,"P4") -> 0 | G22: =COUNTIF('前台-诚心售订单操作与状态流转'!C3:C1000,"P5") -> 0
A23: 前台-服务列表隔离与跨Tab一致性 | B23: =COUNTA('前台-服务列表隔离与跨Tab一致性'!A3:A1000) -> 6 | C23: =COUNTIF('前台-服务列表隔离与跨Tab一致性'!C3:C1000,"P1") -> 0 | D23: =COUNTIF('前台-服务列表隔离与跨Tab一致性'!C3:C1000,"P2") -> 2 | E23: =COUNTIF('前台-服务列表隔离与跨Tab一致性'!C3:C1000,"P3") -> 4 | F23: =COUNTIF('前台-服务列表隔离与跨Tab一致性'!C3:C1000,"P4") -> 0 | G23: =COUNTIF('前台-服务列表隔离与跨Tab一致性'!C3:C1000,"P5") -> 0
A24: 后台-诚心售订单管理 | B24: =COUNTA('后台-诚心售订单管理'!A3:A1000) -> 7 | C24: =COUNTIF('后台-诚心售订单管理'!C3:C1000,"P1") -> 0 | D24: =COUNTIF('后台-诚心售订单管理'!C3:C1000,"P2") -> 5 | E24: =COUNTIF('后台-诚心售订单管理'!C3:C1000,"P3") -> 2 | F24: =COUNTIF('后台-诚心售订单管理'!C3:C1000,"P4") -> 0 | G24: =COUNTIF('后台-诚心售订单管理'!C3:C1000,"P5") -> 0
A25: 后台-资金状态与履约奖励配置 | B25: =COUNTA('后台-资金状态与履约奖励配置'!A3:A1000) -> 7 | C25: =COUNTIF('后台-资金状态与履约奖励配置'!C3:C1000,"P1") -> 0 | D25: =COUNTIF('后台-资金状态与履约奖励配置'!C3:C1000,"P2") -> 5 | E25: =COUNTIF('后台-资金状态与履约奖励配置'!C3:C1000,"P3") -> 1 | F25: =COUNTIF('后台-资金状态与履约奖励配置'!C3:C1000,"P4") -> 1 | G25: =COUNTIF('后台-资金状态与履约奖励配置'!C3:C1000,"P5") -> 0
A26: 合计 | B26: =SUM(B20:B25) -> 40 | C26: =SUM(C20:C25) -> 2 | D26: =SUM(D20:D25) -> 22 | E26: =SUM(E20:E25) -> 14 | F26: =SUM(F20:F25) -> 2 | G26: =SUM(G20:G25) -> 0
A28: 测试结果汇总
A29: 结果 | B29: 数量 | C29: 占比 | D29: 说明
A30: PASS | B30: =COUNTIF('前台-诚心售Tab入口与图标展示'!I3:I1000,"*PASS*")+COUNTIF('前台-诚心售订单列表与状态筛选'!I3:I1000,"*PASS*")+COUNTIF('前台-诚心售订单操作与状态流转'!I3:I1000,"*PASS*")+COUNTIF('前台-服务列表隔离与跨Tab一致性'!I3:I1000,"*PASS*")+COUNTIF('后台-诚心售订单管理'!I3:I1000,"*PASS*")+COUNTIF('后台-资金状态与履约奖励配置'!I3:I1000,"*PASS*") -> 39 | C30: =IF(B30=0,0,B30/B34) -> 0.975 | D30: 通过
A31: FAIL | B31: =COUNTIF('前台-诚心售Tab入口与图标展示'!I3:I1000,"*FAIL*")+COUNTIF('前台-诚心售订单列表与状态筛选'!I3:I1000,"*FAIL*")+COUNTIF('前台-诚心售订单操作与状态流转'!I3:I1000,"*FAIL*")+COUNTIF('前台-服务列表隔离与跨Tab一致性'!I3:I1000,"*FAIL*")+COUNTIF('后台-诚心售订单管理'!I3:I1000,"*FAIL*")+COUNTIF('后台-资金状态与履约奖励配置'!I3:I1000,"*FAIL*") -> 1 | C31: =IF(B31=0,0,B31/B34) -> 0.025 | D31: 失败
A32: TWD | B32: =COUNTIF('前台-诚心售Tab入口与图标展示'!I3:I1000,"*TWD*")+COUNTIF('前台-诚心售订单列表与状态筛选'!I3:I1000,"*TWD*")+COUNTIF('前台-诚心售订单操作与状态流转'!I3:I1000,"*TWD*")+COUNTIF('前台-服务列表隔离与跨Tab一致性'!I3:I1000,"*TWD*")+COUNTIF('后台-诚心售订单管理'!I3:I1000,"*TWD*")+COUNTIF('后台-资金状态与履约奖励配置'!I3:I1000,"*TWD*") -> 0 | C32: =IF(B32=0,0,B32/B34) -> 0 | D32: 待确认
A33: 未测 | B33: =B26-B30-B31-B32 -> 0 | C33: =IF(B33=0,0,B33/B34) -> 0 | D33: 未执行测试
A34: 合计 | B34: =B26 -> 40 | C34: =IF(B34=0,0,1) -> 1

Sheet 缺失分析与优化记录
A1: 诚心售2.0 - 缺失分析与优化记录
A3: 编号 | B3: 缺失/优化项 | C3: 原因分析 | D3: 处理措施 | E3: 严重度 | F3: 状态 | G3: 产品确认结果
A4: G001 | B4: 诚心售Tab排序位置 | C4: 需求未明确诚心售Tab在Tab栏中的具体排序(服务列表前/后) | D4: 用例CX-FE-TAB-003标注待确认,需产品提供排序定义 | E4: 中 | F4: 已确认 | G4: 在卖家交易订单中，并列在买家订单售后列表的右边
A5: G002 | B5: 诚心售Tab URL路由规则 | C5: URL参数格式和路由规则未明确 | D5: 用例CX-FE-TAB-005标注待确认,需技术确认URL方案 | E5: 中 | F5: 已确认 | G5: 暂不考虑
A6: G003 | B6: 诚心卖资金状态具体流转值 | C6: 资金状态从「待处理」流转到什么状态未明确 | D6: 用例CX-FE-OP-005标注待确认,需产品确认资金状态枚举 | E6: 高 | F6: 已确认 | G6: 诚心售在订单交易完成时发放奖励
A7: G004 | B7: 履约奖励发放时机 | C7: 触发条件(租期到期/确认交易完成/其他)未明确 | D7: 用例CX-FE-OP-006和CX-BE-CFG-004标注待确认,需产品确认 | E7: 高 | F7: 已确认 | G7: 仅交易完成才会有诚心售奖励（只有交易才能使用诚心售；并且还得用户自己购买服务）
A8: G005 | B8: 配置变更对已存在订单影响策略 | C8: 配置变更是否仅对新订单生效未明确 | D8: 用例CX-BE-CFG-006标注待确认,需产品确认影响范围 | E8: 高 | F8: 已确认 | G8: 对已经完成的和正在正常开启诚心售不做影响，将要开启的进行变化（以下单购买服务时，系统的实时情况进行判断）
A9: G006 | B9: 后台诚心售角色定义 | C9: 是否有独立的「诚心售管理员」角色未明确 | D9: 用例CX-BE-MG-006标注待确认,需确认角色定义 | E9: 中 | F9: 已确认 | G9: 后台有专门的功能模块
A10: G007 | B10: 诚心售订单是否支持跨Tab搜索 | C10: 是否需要全局搜索功能未明确 | D10: 用例CX-FE-ISO-005标注待确认,需产品确认 | E10: 低 | F10: 已确认 | G10: 支持搜索功能
A11: G008 | B11: 后台诚心售管理菜单层级 | C11: 是一级菜单还是二级菜单未明确 | D11: 需产品确认菜单层级位置 | E11: 低 | F11: 已确认 | G11: 在一级营销管理模块下的子模块

Sheet 前台-诚心售Tab入口与图标展示
A1: 诚心售2.0 - 前台-诚心售Tab入口与图标展示
A2: 用例编号 | B2: 测试项 | C2: 优先级 | D2: 归属版本 | E2: 前置条件 | F2: 输入/执行步骤 | G2: 预计结果 | H2: 实际结果 | I2: 是否通过
A3: CX-FE-TAB-001 | B3: 诚心售Tab入口存在性验证 | C3: P2 | D3: V2.0 | E3: 1.登录账号租赁平台 2.进入个人中心>订单中心 | F3: 1.进入个人中心-订单中心页面 2.查看顶部Tab栏区域 3.确认Tab项列表 | G3: 1.顶部Tab栏显示「诚心售」Tab项 2.Tab与「买家订单」「售后列表」「服务列表」并列显示 3.Tab文字清晰可读无乱码 4.Tab可被点击选中 | H3: 展示正常，功能正常 | I3: PASS
A4: CX-FE-TAB-002 | B4: 诚心售Tab橙色盾牌图标显示 | C4: P3 | D4: V2.0 | E4: 1.登录平台进入个人中心-订单中心 | F4: 1.查看「诚心售」Tab项的图标区域 2.对比1.0版本诚心售履约服务图标 3.检查图标在不同分辨率下显示 | G4: 1.诚心售Tab左侧或上方显示橙色盾牌图标 2.图标样式与1.0诚心售履约服务盾牌图标一致 3.图标清晰无变形无裂图 4.图标尺寸与Tab文字比例协调 | H4: 展示正常 | I4: PASS
A5: CX-FE-TAB-003 | B5: 诚心售Tab排序位置验证 | C5: P3 | D5: V2.0 | E5: 1.登录平台进入个人中心-订单中心 | F5: 1.查看Tab栏从左到右的排列顺序 2.记录各Tab位置 3.刷新页面验证排序稳定性 | G5: 1.Tab排序为:买家订单|售后列表|诚心售(在最右侧,并列在买家订单售后列表的右边) 2.刷新后排序保持一致 3.排序位置固定不可拖拽调整 | H5: 展示支持，不可拖拽 | I5: PASS
A6: CX-FE-TAB-004 | B6: 诚心售Tab选中态高亮验证 | C6: P3 | D6: V2.0 | E6: 1.登录平台进入个人中心-订单中心 | F6: 1.点击「诚心售」Tab 2.观察Tab选中态样式 3.点击其他Tab再切回诚心售 | G6: 1.选中「诚心售」时显示橙色下划线高亮 2.未选中时无下划线文字为常规色 3.切换其他Tab后诚心售高亮消失 4.切回后高亮恢复 5.选中态样式与其他Tab一致 | H6: 诚心售按钮高亮，展示正常 | I6: PASS
A7: CX-FE-TAB-005 | B7: 诚心售Tab点击切换与URL状态 | C7: P2 | D7: V2.0 | E7: 1.登录平台进入个人中心-订单中心 2.浏览器地址栏可观察 | F7: 1.点击「诚心售」Tab 2.观察页面内容区域变化 3.复制当前URL在新标签打开 4.刷新页面 | G7: 1.点击后内容区切换为诚心售订单列表 2.刷新后保持诚心售Tab选中态 3.浏览器前进后退可切换Tab 注:URL路由规则暂不考虑,不验证URL参数 | H7: 点击状态良好，状态流转无异常 | I7: PASS
A8: CX-FE-TAB-006 | B8: 诚心售Tab空状态展示 | C8: P4 | D8: V2.0 | E8: 1.登录无诚心售订单的测试账号 2.进入个人中心-订单中心 | F8: 1.点击「诚心售」Tab 2.观察列表区域显示 3.检查空状态文案与图标 | G8: 1.列表区域显示空状态提示(如「暂无诚心售订单」) 2.空状态有对应的图标或插画 3.文案准确无错别字 4.不显示无关的订单数据 5.空状态不与其他Tab混淆 | H8: 服务列表显示全部：待支付、已开通、已取消、已违约、已成交 | I8: PASS

Sheet 前台-诚心售订单列表与状态筛选
A1: 诚心售2.0 - 前台-诚心售订单列表与状态筛选
A2: 用例编号 | B2: 测试项 | C2: 优先级 | D2: 归属版本 | E2: 前置条件 | F2: 输入/执行步骤 | G2: 预计结果 | H2: 实际结果 | I2: 是否通过
A3: CX-FE-LST-001 | B3: 诚心售订单列表默认展示(全部) | C3: P2 | D3: V2.0 | E3: 1.登录有诚心售订单的账号 2.进入个人中心-订单中心 3.点击「诚心售」Tab | F3: 1.查看状态筛选栏默认选中项 2.查看订单列表展示 3.检查列表排序规则 | G3: 1.默认选中「全部」状态筛选 2.列表展示当前用户所有诚心售订单 3.订单按时间倒序排列(或其他确认规则) 4.每条订单以卡片形式展示 5.右上角显示「成交订单:X」统计数 | H3: 显示所有诚心售订单 | I3: PASS
A4: CX-FE-LST-002 | B4: 待支付状态筛选验证 | C4: P2 | D4: V2.0 | E4: 1.登录有诚心售订单的账号 2.进入诚心售Tab | F4: 1.点击「待支付」状态筛选 2.查看列表展示的订单 3.逐条核对订单状态 | G4: 1.列表仅显示状态为「待支付」的诚心售订单 2.不显示已开通/已取消/已违约/已成交订单 3.订单卡片状态标签显示「待支付」(橙色) 4.待支付订单显示「去支付」「取消订单」按钮 5.无符合订单时显示空状态 | H4: 展示正常 | I4: PASS
A5: CX-FE-LST-003 | B5: 已开通状态筛选验证 | C5: P2 | D5: V2.0 | E5: 1.登录有诚心售订单的账号 2.进入诚心售Tab | F5: 1.点击「已开通」状态筛选 2.查看列表展示的订单 3.核对订单状态与操作按钮 | G5: 1.列表仅显示状态为「已开通」的诚心售订单 2.订单卡片状态标签显示「已开通」(橙色) 3.已开通订单显示「申请退款」按钮 4.不显示其他状态订单 5.筛选结果与数据库数据一致 | H5: 状态流转正常，显示以及开启诚心售 | I5: PASS
A6: CX-FE-LST-004 | B6: 已取消/已违约/已成交状态筛选验证 | C6: P3 | D6: V2.0 | E6: 1.登录有各类状态诚心售订单的账号 2.进入诚心售Tab | F6: 1.点击「已取消」筛选核对结果 2.点击「已违约」筛选核对结果 3.点击「已成交」筛选核对结果 4.检查各状态订单的操作按钮 | G6: 1.已取消筛选:仅显示已取消订单,状态灰色,无操作按钮 2.已违约筛选:仅显示已违约订单,状态红色/深色,无操作按钮 3.已成交筛选:仅显示已成交订单,状态绿色,无操作按钮 4.各筛选结果互不交叉 5.筛选切换响应及时无残留 | H6: 显示正常 | I6: PASS
A7: CX-FE-LST-005 | B7: 成交订单统计数显示验证 | C7: P3 | D7: V2.0 | E7: 1.登录有已成交诚心售订单的账号 2.进入诚心售Tab | F7: 1.查看右上角「成交订单」统计数 2.切换到「已成交」筛选 3.数已成交订单数量 4.创建新的已成交订单后刷新 | G7: 1.统计数显示为已成交诚心售订单总数 2.统计数与「已成交」筛选下订单数一致 3.新增已成交订单后统计数自动+1 4.统计数不包含其他状态订单 5.统计数不包含普通服务订单(仅诚心售) | H7: 已购买诚心售的商品全部显示 | I7: PASS
A8: CX-FE-LST-006 | B8: 诚心售订单卡片字段完整性 | C8: P2 | D8: V2.0 | E8: 1.登录有诚心售订单的账号 2.进入诚心售Tab | F8: 1.展开订单卡片查看所有字段 2.逐字段核对显示内容 3.对比1.0版本字段 | G8: 1.服务编号:格式JJFW+日期+序号,完整显示 2.客服入口:显示客服图标,可点击 3.服务名称:显示「诚心售履约服务」 4.商品详情:商品编号+总资产+哈夫币+安全箱等属性 5.诚心卖资金状态:显示「待处理」等状态 6.履约奖励发放状态:显示「未发放」等状态 7.价格:显示¥金额 8.操作按钮:按状态显示对应按钮 | H8: 订单状态全部显示 | I8: PASS
A9: CX-FE-LST-007 | B9: 诚心售订单列表分页与加载 | C9: P3 | D9: V2.0 | E9: 1.登录有大量诚心售订单的账号(>20条) 2.进入诚心售Tab | F9: 1.查看列表底部是否有分页或加载更多 2.滚动加载更多订单 3.切换状态筛选后验证分页重置 4.弱网环境测试加载 | G9: 1.列表支持分页或无限滚动加载 2.每次加载条数符合配置(如10/20条) 3.加载更多时显示loading状态 4.切换筛选后分页重置为第一页 5.弱网下加载失败有重试提示 6.无重复订单展示 | H9: 1.页面显示无误 2.弱网情况下，提示服务状态有误，请稍后重试 | I9: PASS

Sheet 前台-诚心售订单操作与状态流转
A1: 诚心售2.0 - 前台-诚心售订单操作与状态流转
A2: 用例编号 | B2: 测试项 | C2: 优先级 | D2: 归属版本 | E2: 前置条件 | F2: 输入/执行步骤 | G2: 预计结果 | H2: 实际结果 | I2: 是否通过
A3: CX-FE-OP-001 | B3: 待支付-去支付操作验证 | C3: P1 | D3: V2.0 | E3: 1.登录有待支付诚心售订单的账号 2.进入诚心售Tab 3.账户余额充足 | F3: 1.点击待支付订单的「去支付」按钮 2.跳转支付页面 3.选择支付方式完成支付 4.返回诚心售Tab查看订单状态 5.检查诚心卖资金状态变化 | G3: 1.点击后跳转支付页面,金额正确 2.支付成功后订单状态变更为「已开通」 3.诚心卖资金状态保持「待处理」(交易完成时才发放奖励) 4.履约奖励发放状态保持「未发放」 5.订单列表自动刷新显示新状态 6.后端并发校验(乐观锁)防止重复支付 7.支付金额与订单价格一致 | H3: 变为已开通 | I3: PASS
A4: CX-FE-OP-002 | B4: 待支付-取消订单操作验证 | C4: P2 | D4: V2.0 | E4: 1.登录有待支付诚心售订单的账号 2.进入诚心售Tab | F4: 1.点击待支付订单的「取消订单」按钮 2.确认取消操作(如有二次确认弹窗) 3.查看订单状态变化 4.检查操作按钮消失 | G4: 1.点击后弹出二次确认 2.确认后订单状态变更为「已取消」 3.已取消订单不显示操作按钮 4.取消操作不可逆(后端状态机校验) 5.取消后诚心卖资金状态保持「待处理」(未支付,无资金流转) 6.列表刷新显示已取消状态 | H4: 1.点击后弹出二次确认 2.确认后订单状态变更为「已取消」 3.已取消订单不显示操作按钮 4.取消操作不可逆(后端状态机校验) 5.取消后诚心卖资金状态保持「待处理」(未支付,无资金流转) 6.列表刷新显示已取消状态 | I4: PASS
A5: CX-FE-OP-003 | B5: 已开通-申请退款操作验证 | C5: P1 | D5: V2.0 | E5: 1.登录有已开通诚心售订单的账号 2.进入诚心售Tab | F5: 1.点击已开通订单的「申请退款」按钮 2.填写退款原因(如有) 3.提交退款申请 4.查看订单状态变化 5.检查资金回退链路 | G5: 1.点击后跳转退款申请页面或弹窗 2.退款原因必填(后端参数校验) 3.提交后订单状态流转为「已退款」 4.诚心卖资金状态同步更新(资金回退) 5.履约奖励发放状态同步更新(如已发放则回退) 6.后端状态机校验防止非法退款 7.退款金额与订单金额一致 8.资金回退到原支付账户 | H5: 已开通可申请关闭 | I5: PASS
A6: CX-FE-OP-004 | B6: 已取消/已违约/已成交-无操作按钮验证 | C6: P3 | D6: V2.0 | E6: 1.登录有各类终态诚心售订单的账号 2.进入诚心售Tab | F6: 1.筛选「已取消」状态检查订单卡片 2.筛选「已违约」状态检查订单卡片 3.筛选「已成交」状态检查订单卡片 4.尝试通过URL直接访问操作接口 | G6: 1.已取消订单卡片无操作按钮区域 2.已违约订单卡片无操作按钮区域 3.已成交订单卡片无操作按钮区域 4.后端状态机校验拦截直接接口调用 5.返回错误提示「当前状态不允许此操作」 6.三种终态均不可逆操作 | H6: 已取消/已违约/已成交-无操作按钮验证 | I6: PASS
A7: CX-FE-OP-005 | B7: 诚心卖资金状态流转验证 | C7: P2 | D7: V2.0 | E7: 1.登录有待支付/已开通诚心售订单的账号 2.进入诚心售Tab | F7: 1.查看待支付订单的资金状态 2.支付后查看资金状态变化 3.退款后查看资金状态变化 4.对比不同状态下的资金状态字段 | G7: 1.待支付时资金状态为「待处理」 2.支付成功后资金状态保持「待处理」(诚心售在订单交易完成时才发放奖励) 3.交易完成后资金状态流转为「已完成」 4.退款后资金状态同步更新(资金回退) 5.资金状态与订单状态联动一致 6.后端并发校验(乐观锁)防止资金状态错乱 | H7: 在订单完成的时候诚心售变为完成状态，退还支付金额和发放奖励 | I7: PASS
A8: CX-FE-OP-006 | B8: 履约奖励发放状态流转验证 | C8: P2 | D8: V2.0 | E8: 1.登录有已开通诚心售订单的账号 2.进入诚心售Tab 3.等待奖励发放条件触发 | F8: 1.查看已开通订单的奖励状态 2.等待触发条件达成(如租期到期/确认收货) 3.查看奖励状态变化 4.退款后查看奖励状态变化 | G8: 1.已开通初期奖励状态为「未发放」 2.交易完成后奖励状态变更为「已发放」(仅交易完成才发放诚心售奖励,且需用户自己购买服务) 3.退款后已发放奖励同步回退(资金回退链路) 4.未发放奖励退款后不发放 5.奖励状态与资金状态联动一致 | H8: 履约奖励发放状态流转验证 | I8: PASS
A9: CX-FE-OP-007 | B9: 订单状态机非法流转拦截验证 | C9: P2 | D9: V2.0 | E9: 1.准备各类状态的诚心售订单 2.使用抓包工具或接口测试 | F9: 1.尝试对已取消订单调用支付接口 2.尝试对已成交订单调用退款接口 3.尝试对已违约订单调用取消接口 4.并发操作同一订单(同时支付+取消) | G9: 1.已取消订单调用支付→后端状态机校验拦截返回错误 2.已成交订单调用退款→拦截(如不允许)返回错误 3.已违约订单调用取消→拦截返回错误 4.并发操作→后端并发校验(乐观锁)拦截仅一个成功 5.所有非法操作不产生数据变更 6.非法操作记录审计日志 | H9: 订单状态机非法流转拦截验证 | I9: PASS

Sheet 前台-服务列表隔离与跨Tab一致性
A1: 诚心售2.0 - 前台-服务列表隔离与跨Tab一致性
A2: 用例编号 | B2: 测试项 | C2: 优先级 | D2: 归属版本 | E2: 前置条件 | F2: 输入/执行步骤 | G2: 预计结果 | H2: 实际结果 | I2: 是否通过
A3: CX-FE-ISO-001 | B3: 服务列表Tab不含诚心售订单验证 | C3: P2 | D3: V2.0 | E3: 1.登录同时有诚心售订单和普通服务订单的账号 2.进入个人中心-订单中心 | F3: 1.点击「诚心售」Tab记录订单列表 2.点击「服务列表」Tab记录订单列表 3.对比两个Tab的订单 4.在服务列表中搜索诚心售订单编号 | G3: 1.诚心售Tab显示诚心售履约服务订单 2.服务列表Tab不显示任何诚心售履约服务订单 3.两个Tab订单无交叉 4.服务列表搜索诚心售订单编号返回空结果 5.服务列表统计数不包含诚心售订单 6.隔离为数据层隔离非仅前端隐藏 | H3: 订单编号唯一；诚心售关联订单ID无误 | I3: PASS
A4: CX-FE-ISO-002 | B4: 诚心售Tab不含普通服务订单验证 | C4: P2 | D4: V2.0 | E4: 1.登录同时有诚心售订单和普通服务订单的账号 2.进入个人中心-订单中心 | F4: 1.点击「诚心售」Tab 2.查看订单列表 3.在诚心售Tab搜索普通服务订单编号 4.对比诚心售Tab与服务列表Tab的订单 | G4: 1.诚心售Tab仅显示诚心售履约服务订单 2.不显示普通服务订单 3.搜索普通服务订单编号返回空结果 4.双向隔离:服务列表无诚心售,诚心售无普通服务 5.隔离在数据层生效非仅前端过滤 | H4: 开启诚心售订单，订单回滚到无货包赔专区；开启了订单页面和列表页面有明显标志 | I4: PASS
A5: CX-FE-ISO-003 | B5: 诚心售Tab与买家订单Tab数据隔离 | C5: P3 | D5: V2.0 | E5: 1.登录同时有诚心售订单和买家订单的账号 2.进入个人中心-订单中心 | F5: 1.点击「买家订单」Tab记录订单 2.点击「诚心售」Tab记录订单 3.对比两个Tab订单是否有交叉 4.检查买家订单统计数是否包含诚心售 | G5: 1.买家订单Tab不显示诚心售履约服务订单 2.诚心售Tab不显示买家订单 3.两个Tab数据完全隔离 4.买家订单统计数包含诚心售订单 5.各Tab独立维护筛选状态 | H5: 包含诚心售订单，订单与普通订单不隔离 | I5: PASS
A6: CX-FE-ISO-004 | B6: 跨Tab状态筛选独立性验证 | C6: P3 | D6: V2.0 | E6: 1.登录有各类订单的账号 2.进入个人中心-订单中心 | F6: 1.在诚心售Tab选择「待支付」筛选 2.切换到服务列表Tab查看筛选状态 3.切回诚心售Tab查看筛选是否保持 4.在服务列表Tab选择「已开通」筛选后切换 | G6: 1.诚心售Tab筛选状态独立保存 2.切换Tab后诚心售筛选状态保持 3.服务列表Tab筛选不受诚心售影响 4.各Tab筛选互不干扰 5.刷新后各Tab保持各自筛选状态 | H6: 诚心服务页面单独显示只有开启过诚心售的订单 | I6: PASS
A7: CX-FE-ISO-005 | B7: 诚心售订单搜索范围隔离验证 | C7: P3 | D7: V2.0 | E7: 1.登录有诚心售订单的账号 2.记录一个诚心售订单编号 3.进入个人中心-订单中心 | F7: 1.在诚心售Tab搜索该订单编号 2.切换到服务列表Tab搜索同一编号 3.切换到买家订单Tab搜索同一编号 4.检查各Tab搜索结果 | G7: 1.诚心售Tab搜索返回该诚心售订单 2.服务列表Tab搜索返回空结果 3.买家订单Tab搜索返回空结果 4.搜索范围为当前Tab作用域 5.支持搜索功能,但搜索范围限于当前Tab(不跨Tab搜索) | H7: 支持对订单进行搜索服务；也开启筛选功能 | I7: PASS
A8: CX-FE-ISO-006 | B8: 诚心售Tab与服务列表Tab统计数隔离 | C8: P3 | D8: V2.0 | E8: 1.登录有诚心售订单和普通服务订单的账号 2.进入个人中心-订单中心 | F8: 1.诚心售Tab查看「成交订单」统计数 2.服务列表Tab查看「成交订单」统计数 3.手动统计两个Tab的已成交订单数 4.验证统计数不互相包含 | G8: 1.诚心售Tab成交订单数=诚心售已成交订单数 2.服务列表Tab成交订单数=普通服务已成交订单数 3.两个统计数独立计算互不包含 4.统计数随订单状态变化动态更新 5.统计数为后端动态计算非硬编码 | H8: 单独看诚心售的订单，了解诚心订单的状态、金额 | I8: PASS

Sheet 后台-诚心售订单管理
A1: 诚心售2.0 - 后台-诚心售订单管理
A2: 用例编号 | B2: 测试项 | C2: 优先级 | D2: 归属版本 | E2: 前置条件 | F2: 输入/执行步骤 | G2: 预计结果 | H2: 实际结果 | I2: 是否通过
A3: CX-BE-MG-001 | B3: 后台诚心售订单列表展示验证 | C3: P2 | D3: V2.0 | E3: 1.登录后台管理系统(有诚心售管理权限) 2.进入诚心售管理模块 | F3: 1.查看诚心售订单列表页面 2.检查列表字段 3.验证列表数据来源 4.对比前台诚心售Tab数据 | G3: 1.后台有独立的诚心售订单管理页面 2.列表显示字段:服务编号/用户/商品/状态/资金状态/奖励状态/金额/时间 3.列表数据与前台诚心售Tab数据一致 4.不包含普通服务订单 5.支持按时间倒序排列 6.列表数据后端参数校验(必填/格式) | H3: 后台显示正常 | I3: PASS
A4: CX-BE-MG-002 | B4: 后台诚心售订单搜索验证 | C4: P3 | D4: V2.0 | E4: 1.登录后台管理系统 2.进入诚心售订单管理 | F4: 1.按服务编号搜索 2.按商品编号搜索 3.按用户ID/用户名搜索 4.按订单状态搜索 5.组合条件搜索 6.搜索不存在的数据 | G4: 1.服务编号搜索精确匹配 2.商品编号搜索返回关联订单 3.用户ID搜索返回该用户所有诚心售订单 4.状态搜索筛选准确 5.组合搜索为AND条件 6.无结果时显示空状态 7.搜索支持后端分页非全量加载 | H4: 后台显示正常，对订单可以搜索 | I4: PASS
A5: CX-BE-MG-003 | B5: 后台诚心售订单状态筛选验证 | C5: P3 | D5: V2.0 | E5: 1.登录后台管理系统 2.进入诚心售订单管理 | F5: 1.筛选「待支付」状态 2.筛选「已开通」状态 3.筛选「已取消」状态 4.筛选「已违约」状态 5.筛选「已成交」状态 6.筛选「全部」状态 | G5: 1.各状态筛选结果准确 2.待支付:显示待支付订单 3.已开通:显示已开通订单 4.已取消/已违约/已成交:对应状态订单 5.全部:显示所有诚心售订单 6.筛选结果支持分页 7.筛选与搜索可组合使用 | H5: 筛选功能正常 | I5: PASS
A6: CX-BE-MG-004 | B6: 后台诚心售订单详情查看 | C6: P2 | D6: V2.0 | E6: 1.登录后台管理系统 2.进入诚心售订单管理 3.点击某订单查看详情 | F6: 1.点击订单编号或「查看」按钮 2.查看详情页字段 3.查看订单操作日志 4.查看关联商品信息 5.查看资金与奖励记录 | G6: 1.详情页显示完整订单信息 2.包含:服务编号/用户信息/商品详情/订单状态/资金状态/奖励状态/金额/时间线 3.操作日志记录所有状态变更 4.关联商品信息可跳转查看 5.资金与奖励记录显示发放/回退明细 6.详情数据与列表数据一致 | H6: 订单记录完整；无法跳转 | I6: PASS
A7: CX-BE-MG-005 | B7: 后台诚心售订单状态操作验证 | C7: P2 | D7: V2.0 | E7: 1.登录后台管理系统(有操作权限) 2.进入诚心售订单管理 3.选择待支付或已开通订单 | F7: 1.尝试后台修改订单状态 2.尝试标记违约 3.尝试手动完成订单 4.尝试操作终态订单 5.检查操作日志记录 | G7: 1.后台可执行状态流转操作(标记违约/确认成交等) 2.状态变更后前台同步更新 3.操作需二次确认 4.终态订单(已取消/已违约/已成交)不可操作 5.后端状态机校验拦截非法流转 6.所有操作记录审计日志(操作人/时间/前后状态) | H7: 1.后台可执行状态流转操作(标记违约/确认成交等) 2.状态变更后前台同步更新 3.操作需二次确认 4.终态订单(已取消/已违约/已成交)不可操作 5.后端状态机校验拦截非法流转 6.所有操作记录审计日志(操作人/时间/前后状态) | I7: PASS
A8: CX-BE-MG-006 | B8: 后台诚心售管理权限校验(RBAC) | C8: P2 | D8: V2.0 | E8: 1.准备不同角色账号(超管/诚心售管理员/普通客服/无权限) | F8: 1.超管登录访问诚心售管理 2.诚心售管理员登录访问 3.普通客服登录尝试访问 4.无权限账号尝试访问 5.直接输入URL访问 | G8: 1.超管可访问诚心售管理模块 2.后台有专门的功能模块(非独立角色,是功能模块级别的权限控制) 3.普通客服无访问权限菜单不显示 4.无权限账号URL直接访问被拦截 5.后端权限校验(RBAC角色校验)拦截非法请求 6.返回「无权限」提示 7.权限隔离不泄露数据 | H8: 待优化超管和管理员等级；客服等无操作权限 | I8: PASS
A9: CX-BE-MG-007 | B9: 后台诚心售与普通服务订单管理隔离 | C9: P2 | D9: V2.0 | E9: 1.登录后台管理系统 2.分别进入诚心售管理和普通服务订单管理 | F9: 1.诚心售管理列表查看订单 2.普通服务订单管理列表查看订单 3.对比两个列表数据 4.在诚心售管理搜索普通服务订单编号 5.检查两个模块统计数 | G9: 1.诚心售管理仅显示诚心售订单 2.普通服务订单管理不显示诚心售订单 3.两个模块数据完全隔离 4.诚心售管理搜索普通订单返回空 5.两个模块独立统计互不包含 6.隔离为数据层隔离非前端过滤 7.后端接口分离调用 | H9: 1.诚心售管理仅显示诚心售订单 2.普通服务订单管理不显示诚心售订单 3.两个模块数据完全隔离 4.诚心售管理搜索普通订单返回空 5.两个模块独立统计互不包含 6.隔离为数据层隔离非前端过滤 7.后端接口分离调用 | I9: PASS

Sheet 后台-资金状态与履约奖励配置
A1: 诚心售2.0 - 后台-资金状态与履约奖励配置
A2: 用例编号 | B2: 测试项 | C2: 优先级 | D2: 归属版本 | E2: 前置条件 | F2: 输入/执行步骤 | G2: 预计结果 | H2: 实际结果 | I2: 是否通过
A3: CX-BE-CFG-001 | B3: 诚心卖资金状态配置-规则设置 | C3: P2 | D3: V2.0 | E3: 1.登录后台管理系统(有配置权限) 2.进入诚心售-资金状态配置 | F3: 1.查看当前资金状态流转规则 2.修改资金状态流转配置 3.保存配置 4.验证配置生效 5.查看配置变更日志 | G3: 1.配置页显示当前资金状态流转规则 2.可修改资金状态流转规则 3.保存后配置即时生效 4.配置变更记录审计日志 5.后端参数校验(必填/格式/范围) 6.配置变更不影响已完成和正在开启的订单,仅影响将要开启的订单 7.配置页面权限校验(RBAC) | H3: 对已经开通的诚心售不做回滚，对未开启的进行实时同步，以后台当前状态为准 | I3: PASS
A4: CX-BE-CFG-002 | B4: 诚心卖资金状态配置-参数校验 | C4: P3 | D4: V2.0 | E4: 1.登录后台管理系统 2.进入资金状态配置页 | F4: 1.必填项留空提交 2.输入非法格式数据 3.输入超范围数值 4.输入特殊字符 5.提交正常数据 | G4: 1.必填项留空→后端参数校验拦截提示「XX为必填项」 2.非法格式→拦截并提示正确格式 3.超范围数值→拦截并提示范围 4.特殊字符→拦截或转义处理 5.正常数据→保存成功 6.所有校验在前后端双重执行 | H4: 未对诚心售的金额进行限制，超过自动变为Infinity | I4: FAIL
A5: CX-BE-CFG-003 | B5: 履约奖励发放规则配置 | C5: P2 | D5: V2.0 | E5: 1.登录后台管理系统 2.进入诚心售-奖励配置 | F5: 1.查看当前奖励发放规则 2.修改奖励发放规则 3.保存配置 4.验证规则对前台订单的影响 5.查看配置变更日志 | G5: 1.配置页显示当前奖励发放规则 2.可修改发放规则 3.保存后即时生效 4.新规则适用于新生成的奖励(交易完成时发放) 5.已发放奖励不受影响 6.配置变更记录审计日志 7.后端参数校验(必填/格式/范围) | H5: 可更改发放奖励，实时同步给用户 | I5: PASS
A6: CX-BE-CFG-004 | B6: 履约奖励发放时机配置 | C6: P2 | D6: V2.0 | E6: 1.登录后台管理系统 2.进入诚心售-奖励配置 | F6: 1.查看当前发放时机配置 2.修改发放时机(如租期到期/确认收货后) 3.保存配置 4.验证时机变更对订单的影响 5.对比配置前后订单的奖励发放 | G6: 1.配置页显示当前发放时机 2.可修改发放时机条件 3.保存后新订单按新时机发放(交易完成时发放) 4.已有订单按原时机执行 5.时机变更记录审计日志 6.后端状态机校验确保时机合法性 7.并发场景下奖励不重复发放(后端并发校验乐观锁) | H6: 1.配置页显示当前发放时机 2.可修改发放时机条件 3.保存后新订单按新时机发放(交易完成时发放) 4.已有订单按原时机执行 5.时机变更记录审计日志 6.后端状态机校验确保时机合法性 7.并发场景下奖励不重复发放(后端并发校验乐观锁) | I6: PASS
A7: CX-BE-CFG-005 | B7: 资金状态配置并发校验(乐观锁) | C7: P2 | D7: V2.0 | E7: 1.准备两个管理员账号 2.同时打开资金状态配置页 | F7: 1.管理员A修改配置项X 2.管理员B同时修改配置项X为不同值 3.管理员A先保存 4.管理员B后保存 5.检查最终配置值 6.检查审计日志 | G7: 1.管理员A保存成功 2.管理员B保存被拦截(乐观锁冲突) 3.提示「配置已被他人修改请刷新后重试」 4.最终配置值为管理员A的修改 5.审计日志记录两次操作(一成功一失败) 6.后端并发校验(乐观锁/分布式锁)生效 7.不产生配置数据覆盖 | H7: 有乐观锁 | I7: PASS
A8: CX-BE-CFG-006 | B8: 配置变更对已存在订单影响验证 | C8: P2 | D8: V2.0 | E8: 1.准备已开通的诚心售订单 2.登录后台修改资金状态/奖励配置 | F8: 1.记录订单当前资金状态和奖励状态 2.修改资金状态流转规则 3.修改奖励发放规则 4.查看已存在订单的资金状态 5.查看已存在订单的奖励发放 6.对比配置前后订单行为 | G8: 1.配置变更不影响已完成和正在正常开启的诚心售订单 2.已发放奖励不因配置变更而回退 3.将要开启的订单按新配置执行(以下单购买服务时系统的实时情况判断) 4.审计日志记录配置变更与影响范围 5.后端状态机校验确保配置变更不破坏已有数据 | H8: 1.配置变更不影响已完成和正在正常开启的诚心售订单 2.已发放奖励不因配置变更而回退 3.将要开启的订单按新配置执行(以下单购买服务时系统的实时情况判断) 4.审计日志记录配置变更与影响范围 5.后端状态机校验确保配置变更不破坏已有数据 | I8: PASS
A9: CX-BE-CFG-007 | B9: 配置操作审计日志验证 | C9: P4 | D9: V2.0 | E9: 1.登录后台管理系统 2.执行多笔配置操作 3.查看审计日志 | F9: 1.修改资金状态配置 2.修改奖励发放规则 3.修改发放时机 4.查看审计日志列表 5.筛选审计日志 6.验证日志字段完整性 | G9: 1.每笔配置操作生成审计日志 2.日志字段:操作人/操作时间/操作类型/修改前值/修改后值/IP 3.日志不可篡改不可删除 4.日志支持按时间/操作人/类型筛选 5.日志支持分页查看 6.删除配置也记录日志 7.后端权限校验(RBAC)控制日志查看权限 | H9: 1.每笔配置操作生成审计日志 2.日志字段:操作人/操作时间/操作类型/修改前值/修改后值/IP 3.日志不可篡改不可删除 4.日志支持按时间/操作人/类型筛选 5.日志支持分页查看 6.删除配置也记录日志 7.后端权限校验(RBAC)控制日志查看权限 | I9: PASS
