Workbook

Sheet 用例统计
A1: 后台用户等级配置 - 测试用例统计
A3: 优先级定义标准:
A4: P1(阻断级) | B4: 核心配置不可用、资金/权益计算错误、权限绕过、数据不可恢复。发版前必须100%通过
A5: P2(核心功能) | B5: 主要业务规则异常、阈值升降级、启停删除、奖励生命周期异常。发版前必须通过
A6: P3(重要功能) | B6: 搜索筛选、导出、审计、脱敏、异常提示等重要但非阻断问题。发版前应通过
A7: P4(一般功能) | B7: 展示、兼容、交互体验、长文本、空状态等一般问题。可跟随迭代修复
A8: P5(优化建议) | B8: 窄屏适配、无障碍、体验微调等优化建议
A10: 优化说明:
A11: • 统计页使用Excel公式按各用例Sheet动态计算，避免手写聚合数值
A12: • 同类边界值、同对象多字段、同操作多对象已合并为子步骤，避免过度拆分
A13: • 权限、安全、审计、缓存一致性、导出脱敏、搜索筛选分页等后台通用风险已补充
A14: • 8个待确认项(G002/G010-G016)已全部确认为已确认，新增用户确认说明列
A16: 模块 | B16: 用例数 | C16: P1 | D16: P2 | E16: P3 | F16: P4 | G16: P5
A17: 列表展示与字段校验 | B17: =COUNTA(列表展示与字段校验!A3:A200) -> 9 | C17: =COUNTIF(列表展示与字段校验!C3:C200,"P1") -> 1 | D17: =COUNTIF(列表展示与字段校验!C3:C200,"P2") -> 6 | E17: =COUNTIF(列表展示与字段校验!C3:C200,"P3") -> 1 | F17: =COUNTIF(列表展示与字段校验!C3:C200,"P4") -> 1 | G17: =COUNTIF(列表展示与字段校验!C3:C200,"P5") -> 0
A18: 等级新增编辑配置 | B18: =COUNTA(等级新增编辑配置!A3:A200) -> 9 | C18: =COUNTIF(等级新增编辑配置!C3:C200,"P1") -> 1 | D18: =COUNTIF(等级新增编辑配置!C3:C200,"P2") -> 6 | E18: =COUNTIF(等级新增编辑配置!C3:C200,"P3") -> 1 | F18: =COUNTIF(等级新增编辑配置!C3:C200,"P4") -> 1 | G18: =COUNTIF(等级新增编辑配置!C3:C200,"P5") -> 0
A19: 经验阈值与升降级 | B19: =COUNTA(经验阈值与升降级!A3:A200) -> 9 | C19: =COUNTIF(经验阈值与升降级!C3:C200,"P1") -> 3 | D19: =COUNTIF(经验阈值与升降级!C3:C200,"P2") -> 5 | E19: =COUNTIF(经验阈值与升降级!C3:C200,"P3") -> 1 | F19: =COUNTIF(经验阈值与升降级!C3:C200,"P4") -> 0 | G19: =COUNTIF(经验阈值与升降级!C3:C200,"P5") -> 0
A20: 权益折扣与奖励生命周期 | B20: =COUNTA(权益折扣与奖励生命周期!A3:A200) -> 10 | C20: =COUNTIF(权益折扣与奖励生命周期!C3:C200,"P1") -> 2 | D20: =COUNTIF(权益折扣与奖励生命周期!C3:C200,"P2") -> 8 | E20: =COUNTIF(权益折扣与奖励生命周期!C3:C200,"P3") -> 0 | F20: =COUNTIF(权益折扣与奖励生命周期!C3:C200,"P4") -> 0 | G20: =COUNTIF(权益折扣与奖励生命周期!C3:C200,"P5") -> 0
A21: 状态停用删除与序号规则 | B21: =COUNTA(状态停用删除与序号规则!A3:A200) -> 10 | C21: =COUNTIF(状态停用删除与序号规则!C3:C200,"P1") -> 0 | D21: =COUNTIF(状态停用删除与序号规则!C3:C200,"P2") -> 8 | E21: =COUNTIF(状态停用删除与序号规则!C3:C200,"P3") -> 2 | F21: =COUNTIF(状态停用删除与序号规则!C3:C200,"P4") -> 0 | G21: =COUNTIF(状态停用删除与序号规则!C3:C200,"P5") -> 0
A22: 权限审计与安全可见性 | B22: =COUNTA(权限审计与安全可见性!A3:A200) -> 9 | C22: =COUNTIF(权限审计与安全可见性!C3:C200,"P1") -> 1 | D22: =COUNTIF(权限审计与安全可见性!C3:C200,"P2") -> 6 | E22: =COUNTIF(权限审计与安全可见性!C3:C200,"P3") -> 2 | F22: =COUNTIF(权限审计与安全可见性!C3:C200,"P4") -> 0 | G22: =COUNTIF(权限审计与安全可见性!C3:C200,"P5") -> 0
A23: 兼容性性能与回归 | B23: =COUNTA(兼容性性能与回归!A3:A200) -> 9 | C23: =COUNTIF(兼容性性能与回归!C3:C200,"P1") -> 0 | D23: =COUNTIF(兼容性性能与回归!C3:C200,"P2") -> 3 | E23: =COUNTIF(兼容性性能与回归!C3:C200,"P3") -> 2 | F23: =COUNTIF(兼容性性能与回归!C3:C200,"P4") -> 3 | G23: =COUNTIF(兼容性性能与回归!C3:C200,"P5") -> 1
A24: 合计 | B24: =SUM(B17:B23) -> 65 | C24: =SUM(C17:C23) -> 8 | D24: =SUM(D17:D23) -> 42 | E24: =SUM(E17:E23) -> 9 | F24: =SUM(F17:F23) -> 5 | G24: =SUM(G17:G23) -> 1
A26: =CONCATENATE("P1占比: ",C24,"/",B24," = ",TEXT(C24/B24*100,"0.0"),"% (",IF(C24/B24*100<=15,"✓符合≤15%","✗超出15%"),")") -> P1占比: 8/65 = 12.3% (✓符合≤15%)

Sheet 缺失分析与优化记录
A1: 后台用户等级配置 - 缺失分析与优化记录
A3: 编号 | B3: 缺失/优化项 | C3: 原因分析 | D3: 处理措施 | E3: 严重度 | F3: 状态 | G3: 用户确认说明
A4: G002 | B4: 经验金额小数取整规则需确认 | C4: 需求仅说明消费1元=10经验，未说明小数金额、退款或优惠抵扣后的经验口径 | D4: 已确认: 消费为整数为主，小数0.1代表1经验，两分位小数四舍五入 | E4: P1 | F4: 已确认 | G4: 无小数情况，消费为整数为主，如果出现小数0.1代表1经验，两分位小数四舍五入
A5: G003 | B5: 搜索筛选分页未在需求正文明确 | C5: 后台列表常用能力未明确是否本期提供 | D5: 在兼容性性能与回归模块补充搜索、筛选、分页边界用例 | E5: P3 | F5: 已补充
A6: G004 | B6: 导出能力未明确 | C6: 需求未说明等级配置是否支持导出，但后台数据常涉及审计与运营查看 | D6: 按安全项补充导出权限和脱敏验证，若无导出入口则记录为不适用 | E6: P3 | F6: 已补充
A7: G005 | B7: 缓存TTL与失效机制未明确 | C7: 持续权益改后实时生效依赖缓存失效策略 | D7: 在ULC-EXP-008和ULC-BEN-006中验证多端实时一致性 | E7: P2 | F7: 已补充
A8: G006 | B8: 删除非Lv.1等级的具体条件需确认 | C8: 需求仅说明可能需满足无用户才可删除 | D8: 已确认: 只能删除最后等级且无用户存在，不考虑数据迁移 | E8: P1 | F8: 已确认 | G8: 有且只能删除最后的等级且在该等级无用户存在的情况下才能删除，不要考虑数据乔迁问题
A9: G007 | B9: 奖励服务失败补偿机制需确认 | C9: 首次升级奖励发放涉及券服务，需求未说明失败补偿 | D9: 在ULC-BEN-008中覆盖失败、重试和幂等 | E9: P2 | F9: 已补充
A10: G008 | B10: 审计日志字段未明确 | C10: 后台配置变更风险较高，需求未列出审计字段 | D10: 补充操作者、时间、IP、变更前后值等审计断言 | E10: P2 | F10: 已补充
A11: G009 | B11: 会员人数钻取与敏感信息展示范围未明确 | C11: 当前会员人数只读，但是否可钻取用户列表未说明 | D11: 补充脱敏、角色权限、导出一致性验证 | E11: P3 | F11: 已补充
A12: G010 | B12: 权益订单快照规则需确认 | C12: 权益修改实时生效，但历史订单和下单中订单使用新旧配置边界未明确 | D12: 已确认: 历史不管，以实际时间为准 | E12: P1 | F12: 已确认 | G12: 历史不管，以实际时间为准
A13: G011 | B13: 调高阈值时用户正在下单的折扣口径 | C13: 阈值调高触发降级，但用户正在下单过程中，折扣按旧等级还是新等级计算未明确 | D13: 已确认: 按实时等级折扣计算，以下单时为准，不对订单回滚 | E13: P1 | F13: 已确认 | G13: 调高阈值，用户正在下单过程中，折扣按实时等级折扣计算，如果降级或者升级了，无表示，以下单时的折扣为准，不对订单进行回滚
A14: G012 | B14: 删除等级时用户数据迁移规则 | C14: 需求仅说明有用户禁止删除，但若未来允许迁移删除，原等级用户归属未定义 | D14: 已确认: 只能删除最后等级且无用户，不考虑数据迁移 | E14: P2 | F14: 已确认 | G14: 有且只能删除最后的等级且在该等级无用户存在的情况下才能删除，不要考虑数据乔迁问题
A15: G013 | B15: 手动修改用户等级后会员人数同步 | C15: 用户管理模块手动改用户等级时，等级配置页当前会员人数是否实时同步未明确 | D15: 已确认: 手动修改等级成功后，后台数据实时同步 | E15: P2 | F15: 已确认 | G15: 手动修改等级成功后，后台数据实时同步
A16: G014 | B16: 折扣与优惠券叠加计算顺序未定义 | C16: 用户既有等级折扣又持优惠券，先打折再减券还是先减券再打折未在需求中明确 | D16: 已确认: 先优惠券，后应付金额×折扣，最后为付款金额 | E16: P1 | F16: 已确认 | G16: 先优惠劵后以应付金额在乘以折扣，最后的才是付款金额
A17: G015 | B17: 停用等级期间经验积累恢复规则 | C17: 等级停用期间用户积累的经验，在等级重新启用后是否自动恢复该等级身份未明确 | D17: 已确认: 开启新等级时，用户经验值足够就自动升级 | E17: P2 | F17: 已确认 | G17: 有且只能删除最后的等级且在该等级无用户存在的情况下才能删除，当开启新等级情况下有，用户经验值足够就自动升级
A18: G016 | B18: 租金补贴是否支持小数 | C18: 需求示例均为整数(0/+1/+2/+3)，但未明确是否允许小数(如+1.5) | D18: 已确认: 会存小数点情况，最多两分位小数，如9.11 | E18: P3 | F18: 已确认 | G18: 会存小数点情况，要考虑，会有最多两分位小数，如9.11

Sheet 列表展示与字段校验
A1: 后台用户等级配置 - 列表展示与字段校验
A2: 用例编号 | B2: 测试项 | C2: 优先级 | D2: 归属版本 | E2: 前置条件 | F2: 输入/执行步骤 | G2: 预计结果 | H2: 实际结果 | I2: 是否通过
A3: ULC-LS-001 | B3: 等级列表默认字段展示完整性 | C3: P2 | D3: V1.0 | E3: 后台存在Lv.1-Lv.5等级配置数据，管理员已登录 | F3: 1. 进入后台用户等级配置页 2. 查看列表字段、默认排序和操作列 3. 对照需求字段逐项核验：等级序号、名称、所需经验、租金补贴、购买折扣、租赁折扣、代售折扣、免押金、首次升级奖励、积分奖励开关、当前会员人数、状态 4. 检查操作列按钮完整性（编辑/停用/删除） | G3: 展示全部13个字段且无错位、缺失或乱码；等级按Lv.1→Lv.5递增展示；Lv.1操作列无停用和删除按钮，其他等级有编辑/停用/删除按钮 | H3: 展示正常 | I3: PASS
A4: ULC-LS-002 | B4: Lv编号与等级名称映射展示 | C4: P2 | D4: V1.0 | E4: 系统配置Lv.1普通用户、Lv.2青铜、Lv.3白银、Lv.4黄金、Lv.5钻石 | F4: 1. 打开等级列表 2. 核对Lv编号与名称对应关系 3. 编辑Lv.2名称为「青铜会员」并保存 4. 返回列表复核Lv编号是否仍为Lv.2 5. 检查排序是否仍按Lv递增 | G4: Lv编号固定不随名称修改而改变；名称修改后仅展示名称变化；不存在名称修改导致Lv编号错乱或排序变化 | H4: 展示正常 | I4: PASS
A5: ULC-LS-003 | B5: 当前会员人数只读与实时统计 | C5: P2 | D5: V1.0 | E5: 各等级已有不同数量用户；具备数据库或后台统计对照数据 | F5: 1. 查看当前会员人数列 2. 尝试编辑当前会员人数字段 3. 修改经验阈值触发升降级后刷新列表 4. 对照数据库COUNT查询验证人数一致性 5. 在用户管理模块手动修改某用户等级后回到配置页检查人数是否同步 | G5: 当前会员人数仅展示不可编辑；人数与后端统计一致；阈值调整导致用户升降级后人数实时变化；跨模块手动改等级成功后后台数据实时同步，无缓存滞后或负数 | H5: 后台可查看当前等级人数 | I5: PASS
A6: ULC-LS-004 | B6: 等级名称长度与字符边界校验 | C6: P2 | D6: V1.0 | E6: 管理员进入编辑弹窗或编辑页 | F6: 1. 输入1个字、2个字、10个字、11个字名称 2. 输入空格、特殊符号、重复名称 3. 分别点击保存 | G6: 名称2-10字校验生效；空值、纯空格、超长和重复名称被后端参数校验拦截；合法名称保存成功并刷新列表 | H6: 校验完整；保留合法名称 | I6: PASS
A7: ULC-LS-005 | B7: 所需经验字段范围与递增校验 | C7: P1 | D7: V1.0 | E7: 已有Lv.1-Lv.5配置 | F7: 1. 将Lv.1经验设置为0和非0 2. 将非Lv.1经验设置为0、负数、小数、非数字 3. 将某等级经验设置为小于或等于上一级 | G7: Lv.1可设为0；非Lv.1必须为大于0的整数；经验值必须严格大于上一级；非法值由前端提示且由后端参数校验拦截 | H7: 经验值必须严格大于上一级；非法值拦截 | I7: PASS
A8: ULC-LS-006 | B8: 折扣字段范围与整数校验 | C8: P2 | D8: V1.0 | E8: 进入任一等级编辑页 | F8: 1. 对购买折扣、租赁折扣、代售折扣分别输入1、95、100 2. 输入0、101、小数、字母、空值 3. 保存并查看列表展示 | G8: 折扣范围为1-100整数；100展示为无折扣或原价口径；95展示为9.5折口径；非法值不可保存且错误提示明确 | H8: 展示正常 | I8: PASS
A9: ULC-LS-007 | B9: 租金补贴比例字段展示与计算提示 | C9: P2 | D9: V1.0 | E9: 等级配置页可编辑租金补贴比例 | F9: 1. 查看租金补贴比例说明 2. 输入0、1、2、3等合法整数值 3. 输入小数值(如1.5、9.11)验证是否允许保存 4. 输入负数、超过两分位小数(如1.234)、超大值并保存 5. 验证小数保留规则(最多两分位) | G9: 0表示无补贴；合法整数值保存成功；小数允许保存且最多保留两分位(如9.11)；非法值被拦截；页面说明包含买家租金=总价值×100/(卖家比例-收费比例+等级补贴) | H9: 补贴比例正确；非法值被拦截 | I9: PASS
A10: ULC-LS-008 | B10: 长名称和长奖励文案展示不溢出 | C10: P4 | D10: V1.0 | E10: 存在接近10字等级名称和较长首次升级奖励文案 | F10: 1. 配置最长合法名称 2. 配置较长奖励描述 3. 在不同分辨率下查看列表 | G10: 单元格自动换行或省略展示合理；操作按钮不被挤压；悬浮或详情可查看完整内容；不出现遮挡、错行、横向异常滚动 | H10: 文案显示正确无误 | I10: PASS
A11: ULC-LS-009 | B11: 空数据与加载失败展示 | C11: P3 | D11: V1.0 | E11: 可模拟接口返回空数组、超时或500错误 | F11: 1. 模拟列表无数据 2. 模拟列表接口超时 3. 模拟服务端500错误 | G11: 空数据展示空状态文案；超时/500展示错误提示和重试入口；不展示旧数据冒充新结果；控制台无未捕获异常 | H11: 备注可选填，超过200字禁止输入；不展示旧数据；空状态无异常无报错 | I11: PASS

Sheet 等级新增编辑配置
A1: 后台用户等级配置 - 等级新增编辑配置
A2: 用例编号 | B2: 测试项 | C2: 优先级 | D2: 归属版本 | E2: 前置条件 | F2: 输入/执行步骤 | G2: 预计结果 | H2: 实际结果 | I2: 是否通过
A3: ULC-CFG-001 | B3: 按序新增等级成功 | C3: P2 | D3: V1.0 | E3: 当前最高等级为Lv.5，系统允许继续新增Lv.6 | F3: 1. 点击新增等级按钮 2. 填写合法名称、经验阈值、折扣、补贴、奖励和状态 3. 保存后查看列表 4. 查看审计日志是否记录新增操作 5. 检查新增等级是否可被用户侧正确读取 | G3: 新增等级序号自动为最高等级+1（Lv.6）；不可手工选择跳号；保存成功后列表新增Lv.6并位于末尾；审计日志记录新增操作者、时间和内容；用户侧可正确读取新等级配置 | H3: 创建成功，显示正常 | I3: PASS
A4: ULC-CFG-002 | B4: 新增等级不可跳号 | C4: P1 | D4: V1.0 | E4: 当前最高等级为Lv.5；具备接口调试能力 | F4: 1. 通过前端尝试新增Lv.7（跳过Lv.6） 2. 通过接口直接提交level=7 3. 查看保存结果和错误提示 4. 查看数据库是否产生Lv.7脏数据 | G4: 前端不提供跳号入口；接口请求被后端参数校验拦截；返回明确错误提示；数据库不产生Lv.7脏数据 | H4: 新增等级不可跳号，为系统自动调整 | I4: PASS
A5: ULC-CFG-003 | B5: 编辑等级基础信息成功 | C5: P2 | D5: V1.0 | E5: 存在非Lv.1等级且无并发编辑 | F5: 1. 编辑等级名称、经验阈值、折扣、补贴、免押金、奖励 2. 保存 3. 刷新页面和重新登录后复核 4. 查看用户侧权益是否读取最新配置 5. 查看审计日志是否记录变更前后值 | G5: 合法修改保存成功；列表、详情和用户权益计算读取最新配置；刷新或重新登录后数据不回退；审计日志记录变更前后值 | H5: 合法修改保存成功；列表、详情和用户权益计算读取最新配置；刷新或重新登录后数据不回退；审计日志记录变更前后值 | I5: PASS
A6: ULC-CFG-004 | B6: 编辑保存失败回滚 | C6: P2 | D6: V1.0 | E6: 可模拟保存接口超时、500或网络断开 | F6: 1. 修改多个字段（名称、经验、折扣、补贴） 2. 保存时模拟接口超时/500/网络断开 3. 查看错误提示是否明确 4. 关闭弹窗后重新进入查看数据 5. 确认前端不误显示保存成功 | G6: 失败时提示明确；前端不误显示保存成功；本地临时修改不污染列表；重新进入仍为保存前配置 | H6: 提示后端接口连接异常 | I6: PASS
A7: ULC-CFG-005 | B7: 并发编辑冲突处理 | C7: P2 | D7: V1.0 | E7: 账号A和账号B同时打开同一等级编辑页 | F7: 1. 账号A修改名称和经验阈值并保存 2. 账号B基于旧数据修改折扣并保存 3. 查看账号B是否收到冲突提示 4. 账号B刷新后重新修改并保存 5. 查看最终配置是否为账号B最新保存值 | G7: 系统通过后端并发校验(乐观锁/版本号)识别旧版本提交；账号B收到冲突提示或需刷新后再保存；不发生静默覆盖；最终配置为最后一次有效保存值 | H7: 发生静默覆盖；保留最后一次有效配置 | I7: PASS
A8: ULC-CFG-006 | B8: 积分奖励开关保存与展示 | C8: P3 | D8: V1.0 | E8: 等级支持积分奖励开关 | F8: 1. 开启某等级积分奖励开关并保存 2. 关闭该开关并保存 3. 查看列表与用户侧积分发放触发 | G8: 开关状态保存后列表展示一致；开启后按配置参与后续积分奖励；关闭后不再触发新增奖励；历史已发积分不被异常回滚 | H8: 开关状态保存后列表展示一致；开启后按配置参与后续积分奖励；关闭后不再触发新增奖励；历史已发积分不被异常回滚 | I8: PASS
A9: ULC-CFG-007 | B9: 首次升级奖励配置合法性 | C9: P2 | D9: V1.0 | E9: 奖励可配置体验券、满减券、折扣券 | F9: 1. 配置单个奖励 2. 配置多个奖励 3. 配置已失效券、下架券、空奖励并保存 | G9: 合法奖励配置成功；已失效或下架券不可选或保存失败；空奖励按产品规则处理并有明确提示；奖励ID与名称展示一致 | H9: 首次升级奖励再第一次升级时发放，回退也不重复发放 | I9: PASS
A10: ULC-CFG-008 | B10: 前后端校验一致性 | C10: P2 | D10: V1.0 | E10: 具备接口调试能力 | F10: 1. 绕过前端直接提交非法名称、非法折扣、非法经验 2. 提交缺少必填字段请求 3. 查看接口响应和数据库 | G10: 后端参数校验(必填/格式/范围)完整生效；非法请求不写库；错误码和错误文案可定位字段 | H10: 字段一致 | I10: PASS
A11: ULC-CFG-009 | B11: 操作取消不保存 | C11: P4 | D11: V1.0 | E11: 进入新增或编辑弹窗 | F11: 1. 修改多个字段 2. 点击取消或关闭弹窗 3. 重新进入并查看数据 | G11: 取消或关闭不保存任何修改；再次进入仍展示原配置；如存在未保存内容可按产品规范提示确认 | H11: 操作取消不保留原先数据 | I11: PASS

Sheet 经验阈值与升降级
A1: 后台用户等级配置 - 经验阈值与升降级
A2: 用例编号 | B2: 测试项 | C2: 优先级 | D2: 归属版本 | E2: 前置条件 | F2: 输入/执行步骤 | G2: 预计结果 | H2: 实际结果 | I2: 是否通过
A3: ULC-EXP-001 | B3: 消费经验计算规则 | C3: P2 | D3: V1.0 | E3: 用户完成支付订单，订单金额包含可获得经验的消费金额 | F3: 1. 创建金额为1元、10元、99.9元订单并完成支付 2. 查看用户累计经验和经验流水明细 3. 验证经验计算公式：消费1元=10经验值 4. 验证小数处理：消费为整数为主，如出现小数0.1代表1经验，两分位小数四舍五入 5. 模拟订单退款后查看经验是否扣减 6. 核对经验流水、累计经验和等级匹配结果三者一致性 | G3: 按消费1元=10经验值计算；消费以整数为主，小数0.1=1经验，两分位小数四舍五入(如99.9元=999经验)；退款后经验正确扣减；经验流水、累计经验和等级匹配结果一致
A4: ULC-EXP-002 | B4: 达到阈值自动升级 | C4: P1 | D4: V1.0 | E4: 用户当前经验低于下一等级阈值 | F4: 1. 记录用户当前等级和经验 2. 让用户消费后累计经验刚好达到下一等级阈值 3. 查看用户等级是否自动升级 4. 查看持续权益是否切换到新等级 5. 查看首次升级奖励是否按新等级发放一次 6. 查看后台会员人数统计是否同步变化 | G4: 累计经验达到阈值时自动升级；持续权益切换到新等级；首次升级奖励按新等级发放一次；会员人数统计同步变化 | H4: 达到等级系统对用户自动升级，自动享受当前等级权益，并且发放等级优惠劵 | I4: PASS
A5: ULC-EXP-003 | B5: 未达到阈值不升级 | C5: P2 | D5: V1.0 | E5: 用户当前经验接近下一等级阈值 | F5: 1. 记录用户当前等级和经验 2. 让用户消费后累计经验差1点达到阈值 3. 刷新用户信息查看等级 4. 查看后台会员人数是否变化 5. 查看是否误发放下一等级奖励 6. 查看权益是否仍按原等级计算 | G5: 用户等级保持不变；不会提前发放下一等级奖励；后台人数和权益仍按原等级计算 | H5: 用户等级保持不变；不会提前发放下一等级奖励；后台人数和权益仍按原等级计算 | I5: PASS
A6: ULC-EXP-004 | B6: 调高阈值触发被动降级 | C6: P1 | D6: V1.0 | E6: 某等级已有用户，且部分用户经验低于调高后的阈值 | F6: 1. 记录受影响用户数量和当前权益 2. 后台调高该等级所需经验并保存 3. 等待等级重算完成后查看受影响用户等级 4. 验证降级用户持续权益是否切换为降级后等级 5. 查看后台会员人数是否实时更新 6. 查看降级记录是否可追溯 7. 模拟用户正在下单时调高阈值，验证折扣口径 | G6: 经验不满足新阈值的用户降级到满足条件的最高等级；持续权益切换为降级后等级；会员人数实时更新；降级记录可追溯；正在下单用户折扣按实时等级折扣计算，以下单时为准，不对订单进行回滚 | H6: 更改等级经验需求，用户等级更具实时等级经验要求变得，低于变为下一级，高于升为上一级；不会对已经形成的订单进行回滚 | I6: PASS
A7: ULC-EXP-005 | B7: 调低阈值触发自动升级 | C7: P1 | D7: V1.0 | E7: 低等级用户经验高于调低后的新阈值 | F7: 1. 记录满足条件的用户数量 2. 后台调低高等级所需经验并保存 3. 触发等级重算 4. 查看满足条件用户是否自动升级 5. 验证首次升级奖励是否按规则发放 6. 验证持续权益是否实时生效 7. 查看会员人数更新是否准确 | G7: 满足新阈值的低等级用户自动升级；首次升级奖励按规则发放；持续权益实时生效；会员人数更新准确 | H7: 满足新阈值的低等级用户自动升级；首次升级奖励按规则发放；持续权益实时生效；会员人数更新准确 | I7: PASS
A8: ULC-EXP-006 | B8: 调高阈值后再次升回等级不重复发一次性奖励 | C8: P2 | D8: V1.0 | E8: 用户Lv.3经验2000已领取Lv.3首次升级奖励；后台将Lv.3阈值从2000调高至10000 | F8: 1. 后台将Lv.3阈值调至10000并保存 2. 确认用户降级为Lv.2（经验2000<10000） 3. 用户继续消费使经验达到10000 4. 查看用户等级、奖励发放记录和持续权益 | G8: 用户重新升回Lv.3；系统正确识别该用户曾拥有Lv.3，不重复发放Lv.3首次升级奖励；持续权益（折扣/补贴）正确恢复为Lv.3标准；奖励流水无重复记录 | H8: 不重复发放等级优惠劵；持续权益（折扣/补贴）正确恢复为Lv.3标准；奖励流水无重复记录 | I8: PASS
A9: ULC-EXP-007 | B9: 跨多级升级奖励发放策略与人数流转 | C9: P2 | D9: V1.0 | E9: 用户Lv.1经验0；各等级阈值Lv.2=500/Lv.3=2000/Lv.4=10000/Lv.5=50000 | F9: 1. 模拟用户一次性获得50000经验（从Lv.1直接跳到Lv.5） 2. 查看用户最终等级和奖励领取记录 3. 确认只发放目标等级(Lv.5)奖励，不补发中间等级(Lv.2/Lv.3/Lv.4)奖励 4. 查看Lv.2/Lv.3/Lv.4当前会员人数是否有中间态增加再减少 5. 核对数据库是否存在中间等级的瞬时状态记录 | G9: 用户直接升至Lv.5；只发放Lv.5目标等级奖励，不补发中间等级(Lv.2/Lv.3/Lv.4)奖励；会员人数在各等级间正确流转，Lv.2/3/4人数无异常波动或脏记录 | H9: 直接跳级，中间等级不补发奖励；实时显示各等级人数 | I9: PASS
A10: ULC-EXP-008 | B10: 阈值修改后缓存一致性 | C10: P2 | D10: V1.0 | E10: 用户端、订单结算、后台列表均读取等级权益 | F10: 1. 修改某等级阈值导致用户升降级 2. 立即查看用户端权益、订单折扣、后台人数 3. 多次刷新和重新登录 | G10: 各端读取结果一致；不存在缓存导致旧等级权益继续生效；如有缓存TTL，应符合后端约定并可被主动失效 | H10: 用户等级经验阈值改变，系统不记录原来的的等级情况数据；旧缓存不生效 | I10: PASS
A11: ULC-EXP-009 | B11: 经验重算任务异常恢复 | C11: P3 | D11: V1.0 | E11: 可模拟等级重算任务中断或部分失败 | F11: 1. 修改阈值触发大批量重算 2. 中途模拟任务失败 3. 重试任务并核对结果 | G11: 失败有告警和重试能力；已处理和未处理用户状态可识别；重试后最终一致；不会重复发放一次性奖励 | H11: 系统自动计算会员经验获取，自动发放经验值；不重复发放一次性奖励 | I11: PASS

Sheet 权益折扣与奖励生命周期
A1: 后台用户等级配置 - 权益折扣与奖励生命周期
A2: 用例编号 | B2: 测试项 | C2: 优先级 | D2: 归属版本 | E2: 前置条件 | F2: 输入/执行步骤 | G2: 预计结果 | H2: 实际结果 | I2: 是否通过
A3: ULC-BEN-001 | B3: 购买折扣计算正确 | C3: P1 | D3: V1.0 | E3: 用户处于配置了购买折扣的等级 | F3: 1. 配置购买折扣为100、99、95 2. 分别创建购买订单 3. 核对实际支付金额=订单金额×折扣/100 4. 修改折扣后再次下单验证实时生效 5. 查看历史已支付订单是否被异常改价 | G3: 实际支付=订单金额×折扣/100；100为原价；折扣变化后新订单实时生效；历史已支付订单不被异常改价；金额四舍五入规则一致 | H3: 购买折扣正确计算 | I3: PASS
A4: ULC-BEN-002 | B4: 租赁折扣计算正确 | C4: P2 | D4: V1.0 | E4: 用户处于配置了租赁折扣的等级 | F4: 1. 配置租赁折扣为100、98、95 2. 分别创建租赁订单 3. 核对租赁订单支付金额=订单金额×折扣/100 4. 修改折扣后再次下单验证实时生效 5. 查看历史已支付订单是否被异常改价 | G4: 租赁折扣按配置计算；不同等级用户使用对应折扣；折扣修改后新订单实时生效，历史已支付订单不被异常改价 | H4: 租赁折扣按配置计算；不同等级用户使用对应折扣；折扣修改后新订单实时生效，历史已支付订单不回滚 | I4: PASS
A5: ULC-BEN-003 | B5: 代售费折扣计算正确 | C5: P2 | D5: V1.0 | E5: 用户出售账号并产生代售服务费 | F5: 1. 配置代售费折扣为100、98、95 2. 分别创建代售订单 3. 核对实际代售费=标准代售费×折扣/100 4. 修改折扣后再次创建代售订单验证实时生效 5. 查看费用流水与订单展示是否一致 | G5: 实际代售费=标准代售费×折扣/100；折扣范围和取整规则一致；折扣修改后新订单实时生效；费用流水与订单展示一致 | H5: 折扣为订单金额在优惠劵逻辑之后的应付金额上折扣；折扣修改后，已经完成的和已经生成订单的不进行回滚，将要下单的进行改变， | I5: PASS
A6: ULC-BEN-004 | B6: 租金补贴比例公式正确 | C6: P1 | D6: V1.0 | E6: 存在卖家比例40、收费比例0、等级补贴+2的租赁场景 | F6: 1. 配置等级补贴为+2 2. 创建对应租赁订单 3. 核对买家租金=总价值×100/(卖家比例-收费比例+等级补贴) 4. 验证示例：40×100/42≈95.24 5. 测试异常分母场景（卖家比例-收费比例+补贴≤0） | G6: 买家租金=总价值×100/(卖家比例-收费比例+等级补贴)；示例40×100/42≈95.24计算正确；异常分母被后端参数校验拦截，不允许生成非法租金 | H6: 租金补贴比例公式正确 | I6: PASS
A7: ULC-BEN-005 | B7: 免押金权益生效 | C7: P2 | D7: V1.0 | E7: Lv.4及以上配置免押金为是，低等级为否 | F7: 1. 使用Lv.3用户创建租赁订单查看押金项 2. 使用Lv.4用户创建租赁订单查看押金项 3. 修改免押金开关后再次分别下单 4. 查看历史已支付订单押金是否被异常清除 | G7: Lv.4及以上无需支付押金；低等级仍需押金；开关修改后对新订单实时生效；历史订单押金不被异常清除 | H7: 免押金权益生效，在支付页面下方显示免押金 | I7: PASS
A8: ULC-BEN-006 | B8: 持续权益修改实时生效 | C8: P2 | D8: V1.0 | E8: 用户当前处于被修改权益的等级 | F8: 1. 修改购买折扣、租赁折扣、代售折扣、租金补贴、免押金 2. 保存后立即创建对应业务订单 3. 对比修改前后权益计算结果 4. 查看旧订单是否按下单时快照处理 | G8: 持续权益改后实时生效；新订单按新配置计算；旧订单按下单时快照或既定规则处理，不发生资金不一致 | H8: 持续权益修改实时生效 | I8: PASS
A9: ULC-BEN-007 | B9: 一次性奖励改后不补发 | C9: P2 | D9: V1.0 | E9: 用户已领取某等级首次升级奖励 | F9: 1. 修改该等级首次升级奖励配置 2. 查看已领取用户奖励账户 3. 让新用户首次升到该等级 | G9: 已领取用户不补发新奖励；新首次升级用户按新配置发放；奖励流水能区分配置版本和发放时间 | H9: 一次性奖励改后不补发；新首次升级用户按新配置发放；奖励流水能区分配置版本和发放时间 | I9: PASS
A10: ULC-BEN-008 | B10: 奖励发放失败补偿 | C10: P2 | D10: V1.0 | E10: 可模拟券服务不可用或奖励发放接口失败 | F10: 1. 用户首次升级触发奖励 2. 模拟奖励服务超时或失败 3. 查看补偿任务和用户奖励 | G10: 升级状态不被错误回滚；奖励失败有待补偿记录、重试机制和告警；重试成功后不重复发放多份奖励 | H10: 升级状态不被错误回滚；奖励失败有重试机制；重试成功后不重复发放多份奖励 | I10: PASS
A11: ULC-BEN-009 | B11: 权益配置与订单快照一致性 | C11: P2 | D11: V1.0 | E11: 用户下单过程中后台修改权益配置 | F11: 1. 用户进入下单页获取权益 2. 后台修改等级折扣或补贴 3. 用户提交订单并支付 4. 验证历史订单不受影响，以实际时间为准 | G11: 订单使用明确的权益快照规则；支付金额与订单明细一致；后台修改不会导致前后端金额不一致或支付绕过；历史订单不管，以实际时间为准 | H11: 以下单时用户等级实时权益为准 | I11: PASS
A12: ULC-BEN-010 | B12: 折扣与优惠券叠加计算顺序 | C12: P2 | D12: V1.0 | E12: 用户Lv.3购买折扣98（9.8折），持有10元无门槛优惠券 | F12: 1. 创建100元购买订单 2. 使用优惠券 3. 核对实付金额 4. 验证计算顺序: 先优惠券后应付金额×折扣(100-10=90, 90×0.98=88.2) 5. 确认付款金额=88.2元 | G12: 计算顺序: 先优惠劵后以应付金额在乘以折扣，最后的才是付款金额；实付金额=(100-10)×0.98=88.2元；全链路计算顺序一致；不出现折上折导致资金损失或用户投诉 | H12: 先优惠卷后计算折扣；不出现重复折扣 | I12: PASS

Sheet 状态停用删除与序号规则
A1: 后台用户等级配置 - 状态停用删除与序号规则
A2: 用例编号 | B2: 测试项 | C2: 优先级 | D2: 归属版本 | E2: 前置条件 | F2: 输入/执行步骤 | G2: 预计结果 | H2: 实际结果 | I2: 是否通过
A3: ULC-STS-001 | B3: Lv.1不可停用 | C3: P2 | D3: V1.0 | E3: 列表存在Lv.1普通用户 | F3: 1. 查看Lv.1操作列 2. 尝试通过前端停用Lv.1 3. 通过接口提交停用Lv.1请求 | G3: Lv.1无停用按钮或按钮不可用；接口被后端状态机校验拦截；Lv.1状态保持启用 | H3: LV1不可停用，只能更改属性 | I3: PASS
A4: ULC-STS-002 | B4: Lv.1不可删除 | C4: P2 | D4: V1.0 | E4: 列表存在Lv.1普通用户 | F4: 1. 查看Lv.1操作列 2. 尝试通过接口删除Lv.1 3. 查看列表和数据库 | G4: Lv.1无删除入口；接口删除请求被后端状态机校验拦截；Lv.1数据不被删除 | H4: Lv.1不可删除 | I4: PASS
A5: ULC-STS-003 | B5: 有用户等级禁止停用 | C5: P2 | D5: V1.0 | E5: 某非Lv.1等级当前会员人数大于0 | F5: 1. 点击停用该等级 2. 确认操作 3. 查看状态是否变更 4. 查看该等级已有用户的等级和权益是否受影响 5. 查看列表状态展示 | G5: 系统阻止停用并提示已有用户不可停用；等级仍参与匹配；已有用户等级和权益不受影响 | H5: 只有在等级中没有用户才能删除该等级 | I5: PASS
A6: ULC-STS-004 | B6: 无用户等级停用成功且不参与匹配 | C6: P2 | D6: V1.0 | E6: 某非Lv.1等级会员人数为0 | F6: 1. 停用该等级 2. 查看列表状态是否变更为停用 3. 构造用户经验达到该停用等级阈值 4. 查看用户最终匹配等级是否跳过停用等级 5. 查看停用等级是否不参与升级匹配 | G6: 停用成功；停用等级不参与用户升级匹配；用户匹配到满足条件的最高启用等级；列表状态展示停用 | H6: 进最后一个等级可以删除并且当前等级无用户存在；无用户等级停用成功且不参与匹配 | I6: PASS
A7: ULC-STS-005 | B7: 启用等级阈值范围校验 | C7: P2 | D7: V1.0 | E7: 存在停用等级，其上下相邻启用等级有明确阈值 | F7: 1. 将停用等级阈值设置为不在上下已启用等级范围内 2. 点击启用 3. 修正阈值后再次启用 | G7: 阈值不合法时禁止启用；错误提示说明需大于上一级且小于下一级启用等级阈值；修正后启用成功 | H7: 等级经验有明确校验 | I7: PASS
A8: ULC-STS-006 | B8: 非Lv.1无用户等级删除成功 | C8: P2 | D8: V1.0 | E8: 某最高等级无用户且允许删除 | F8: 1. 点击删除该等级 2. 二次确认 3. 查看列表和后续新增等级 | G8: 删除成功且有二次确认；列表移除该等级；再次新增时序号按当前最高等级+1生成，不出现跳号或重复 | H8: 删除成功且有二次确认；列表移除该等级；再次新增时序号按当前最高等级+1生成，不出现跳号或重复 | I8: PASS
A9: ULC-STS-007 | B9: 有用户等级禁止删除 | C9: P2 | D9: V1.0 | E9: 某非Lv.1等级当前会员人数大于0；或尝试删除非最后等级 | F9: 1. 尝试删除有用户的等级 2. 尝试删除非最后等级(中间等级) 3. 查看响应 4. 查看用户等级和列表 | G9: 有用户的等级删除被阻止；非最后等级删除被阻止；只能删除最后的等级且在该等级无用户存在的情况下才能删除；不考虑数据迁移问题；提示存在用户不可删除或非最后等级不可删除；用户等级、权益、统计不受影响 | H9: 等级被删除了 | I9: FAIL
A10: ULC-STS-008 | B10: 状态切换审计与二次确认 | C10: P3 | D10: V1.0 | E10: 管理员具备启停权限 | F10: 1. 停用等级并确认 2. 启用等级并确认 3. 查看审计日志 | G10: 启停高影响操作有二次确认；审计日志记录操作者、时间、等级、原状态、新状态、原因或备注 | H10: 管理员可以对等级属性进行编辑；功能正常 | I10: PASS
A11: ULC-STS-009 | B11: 排序稳定与序号不可编辑 | C11: P3 | D11: V1.0 | E11: 存在多等级配置 | F11: 1. 刷新列表多次 2. 尝试编辑等级序号 3. 删除/新增后查看排序 | G11: 等级序号系统固定不可编辑；排序始终按Lv递增；新增、删除、启停后排序稳定，不受名称或人数变化影响 | H11: 等级序号系统固定不可编辑；排序始终按Lv递增；新增、删除、启停后排序稳定，不受名称或人数变化影响 | I11: PASS
A12: ULC-STS-010 | B12: 停用等级对新用户升级路径的影响 | C12: P2 | D12: V1.0 | E12: Lv.2处于停用状态，Lv.3阈值2000且启用 | F12: 1. 确认Lv.2已停用且不参与匹配 2. 新用户注册为Lv.1 3. 让用户积累经验达到Lv.2原阈值500 4. 观察用户等级是否停留在Lv.1 5. 继续积累经验达到Lv.3阈值2000 6. 观察用户是否直接跳入Lv.3 7. 重新开启Lv.2，验证用户经验值足够时是否自动升级 | G12: 用户不会进入停用的Lv.2；经验达到停用等级阈值时停留在当前等级；经验达到下一个启用等级阈值时自动跳入该等级；停用等级对升级路径无阻塞性影响；开启新等级情况下，用户经验值足够就自动升级 | H12: 只有删除等级，无法停用等级 | I12: PASS

Sheet 权限审计与安全可见性
A1: 后台用户等级配置 - 权限审计与安全可见性
A2: 用例编号 | B2: 测试项 | C2: 优先级 | D2: 归属版本 | E2: 前置条件 | F2: 输入/执行步骤 | G2: 预计结果 | H2: 实际结果 | I2: 是否通过
A3: ULC-SEC-001 | B3: 无权限用户不可访问配置页 | C3: P2 | D3: V1.0 | E3: 账号无用户等级配置查看权限 | F3: 1. 使用无权限账号访问页面URL 2. 通过菜单查找入口 3. 直接请求列表接口 | G3: 菜单不展示入口；直接访问页面或接口被后端权限校验(RBAC角色校验)拦截；不返回等级配置敏感数据 | H3: 菜单不展示入口；直接访问页面或接口被后端权限校验(RBAC角色校验)拦截；不返回等级配置数据 | I3: PASS
A4: ULC-SEC-002 | B4: 只读权限不可新增编辑删除启停 | C4: P2 | D4: V1.0 | E4: 账号仅有查看权限 | F4: 1. 打开等级配置页 2. 查看操作按钮 3. 直接调用新增、编辑、删除、启停接口 | G4: 页面不展示或禁用写操作按钮；接口写操作被RBAC拦截；仅允许查看列表和详情 | H4: 账号金科查看处于售卖等级，以及享受什么样的权限 | I4: PASS
A5: ULC-SEC-003 | B5: 编辑权限粒度校验 | C5: P2 | D5: V1.0 | E5: 账号具备编辑权限但无删除或启停权限 | F5: 1. 使用该账号编辑等级并保存 2. 尝试删除等级 3. 尝试启停等级 | G5: 编辑操作允许；删除和启停按权限被拦截；错误提示不暴露系统内部信息 | H5: 编辑操作允许；删除和启停按权限被拦截；错误提示不暴露系统内部信息，提示后端接口异常 | I5: PASS
A6: ULC-SEC-004 | B6: 全部配置变更写入审计日志 | C6: P2 | D6: V1.0 | E6: 管理员具备配置权限 | F6: 1. 新增等级并查看审计日志 2. 编辑阈值和权益并查看审计日志 3. 停用/启用/删除等级并查看审计日志 4. 核对每条日志是否记录操作者、时间、IP、操作类型、等级、变更前值、变更后值 5. 验证日志不可被普通管理员篡改 | G6: 每类变更均记录操作者、时间、IP、操作类型、等级、变更前值、变更后值；高危操作（阈值修改/删除）记录修改前值和修改后值；日志不可被普通管理员篡改 | H6: 日志记录不可修改，不可删除，记录每类变更均记录操作者、时间、IP、操作类型、等级、变更前值、变更后值；高危操作（阈值修改/删除）记录修改前值和修改后值 | I6: PASS
A7: ULC-SEC-005 | B7: 接口越权与参数篡改防护 | C7: P1 | D7: V1.0 | E7: 具备抓包或接口调试能力 | F7: 1. 修改请求中的等级ID为无权限数据 2. 修改不可编辑字段如会员人数、等级序号 3. 重放历史保存请求 4. 查看后端是否拦截非法请求 5. 查看数据库是否产生脏数据 | G7: 后端权限校验和参数白名单生效；不可编辑字段被忽略或拦截；重放请求因版本或权限校验失败，不造成脏数据 | H7: 提示接口异常，需要刷新重试 | I7: PASS
A8: ULC-SEC-006 | B8: 导出权限控制 | C8: P3 | D8: V1.0 | E8: 系统提供等级配置导出或后续支持导出 | F8: 1. 无导出权限账号点击导出或请求导出接口 2. 有导出权限账号导出 3. 打开导出文件核对内容 | G8: 无权限不可导出；有权限可导出当前筛选范围数据；导出内容不包含不应暴露的内部字段或接口密钥 | H8: 无导出能力（暂不设计） | I8: PASS
A9: ULC-SEC-007 | B9: 用户数据脱敏规则 | C9: P3 | D9: V1.0 | E9: 配置页或详情可能展示用户样例、会员人数钻取或操作人信息 | F9: 1. 普通管理员查看相关数据 2. 高权限管理员查看 3. 刷新页面或导出 | G9: 手机号、账号ID等敏感数据按角色脱敏；高权限查看需符合权限；刷新和导出后脱敏规则一致 | H9: 用户不可见，管理员可见使用用户民和手机号，客服对身份证等敏感信息不可见 | I9: PASS
A10: ULC-SEC-008 | B10: 配置页对前台用户不可见 | C10: P2 | D10: V1.0 | E10: 普通前台用户已登录 | F10: 1. 前台用户访问后台配置URL 2. 检查前台个人中心、会员页是否出现配置入口 3. 请求后台配置接口 | G10: 前台用户不可见后台配置入口；直接访问被拦截；接口不返回后台配置操作能力 | H10: 前台用户不可见后台配置入口；直接访问被后台拦截；接口不返回后台配置操作能力 | I10: PASS
A11: ULC-SEC-009 | B11: XSS与特殊字符安全 | C11: P2 | D11: V1.0 | E11: 管理员可编辑等级名称或奖励文案 | F11: 1. 输入<script>、HTML标签、SQL特殊字符 2. 保存并查看列表、详情、导出 3. 查看控制台和接口响应 | G11: 恶意脚本被转义或拦截；页面不执行脚本；导出文件不包含可执行公式注入；数据库无异常 | H11: 不执行恶意脚本，直接翻译为纯文本 | I11: PASS

Sheet 兼容性性能与回归
A1: 后台用户等级配置 - 兼容性性能与回归
A2: 用例编号 | B2: 测试项 | C2: 优先级 | D2: 归属版本 | E2: 前置条件 | F2: 输入/执行步骤 | G2: 预计结果 | H2: 实际结果 | I2: 是否通过
A3: ULC-QA-001 | B3: 搜索筛选基础能力 | C3: P3 | D3: V1.0 | E3: 列表支持按等级名称、状态或等级序号搜索筛选；如暂未支持则记录缺失 | F3: 1. 输入完整等级名称搜索 2. 输入部分关键字搜索 3. 按启用/停用状态筛选 | G3: 搜索和筛选结果准确；无结果展示空状态；清空条件后恢复全部数据；如需求未定义搜索筛选，应在缺失分析中记录待产品确认 | H3: 缺失（不需要） | I3: PASS
A4: ULC-QA-002 | B4: 分页边界与每页条数 | C4: P3 | D4: V1.0 | E4: 系统存在足够多等级或可通过测试数据构造 | F4: 1. 切换每页条数 2. 跳转首页、末页、超出页码 3. 删除末页最后一条后刷新 | G4: 分页总数、页码、每页条数正确；超出页码自动回退或提示；删除后页码不空白异常 | H4: 固定有lv1-lv4等级，不创建过多等级 | I4: PASS
A5: ULC-QA-003 | B5: 查询防抖与重复提交 | C5: P4 | D5: V1.0 | E5: 列表搜索输入框和保存按钮可操作 | F5: 1. 快速连续输入搜索词 2. 连续点击保存按钮 3. 查看接口请求次数和最终结果 | G5: 搜索请求有防抖或取消旧请求；保存按钮提交中置灰；不会产生重复保存、重复奖励或重复日志 | H5: 缺失（不需要） | I5: PASS
A6: ULC-QA-004 | B6: 批量自动升降级性能与奖励风暴 | C6: P2 | D6: V1.0 | E6: 构造1000名用户经验在400-500之间（Lv.1），Lv.2阈值当前为500 | F6: 1. 后台将Lv.2阈值从500降至400并保存 2. 监控配置保存接口耗时、重算任务耗时和系统负载 3. 观察1000名用户是否全部升级为Lv.2 4. 监控发券/奖励服务是否扛住1000人同时触发首次升级奖励 5. 检查是否有漏发、重复发或服务崩溃 | G6: 配置保存成功不超时；重算任务异步执行或分批处理，进度可追踪；1000名用户最终全部升级为Lv.2；发券服务无崩溃、无漏发、无重复发；大数据量下最终统计一致 | H6: 目前支持并发500，1000会产生丢包，失败后重新发放，不重复 | I6: PASS
A7: ULC-QA-005 | B7: 列表加载性能 | C7: P4 | D7: V1.0 | E7: 后台存在多等级和较多操作日志 | F7: 1. 首次打开配置页 2. 多次切换筛选条件 3. 记录接口耗时和页面渲染耗时 | G7: 首屏加载、筛选刷新在产品约定性能范围内；无明显卡顿；接口返回字段精简，无冗余大字段 | H7: 后台记录使用操作行为，日志不可删除 | I7: PASS
A8: ULC-QA-006 | B8: 服务端异常容错 | C8: P2 | D8: V1.0 | E8: 可模拟接口超时、鉴权过期、500错误 | F8: 1. 打开列表时模拟异常 2. 保存配置时模拟异常 3. 鉴权过期后继续操作 | G8: 列表异常有重试；保存异常不误提示成功；鉴权过期跳转登录或刷新令牌；用户操作不产生脏数据 | H8: 未误提示成功、无脏数据；但401未跳转、500错误提示验证不充分（XHR拦截限制） | I8: PASS
A9: ULC-QA-007 | B9: 浏览器兼容性 | C9: P4 | D9: V1.0 | E9: 准备Chrome、Edge、Firefox主流版本 | F9: 1. 分别打开等级配置页 2. 执行新增、编辑、启停、筛选 3. 查看样式和控制台 | G9: 主流浏览器下布局、弹窗、表单、按钮、提示一致；无控制台报错；中文和数字格式展示正常 | H9: Chromium下无报错、布局正常 | I9: PASS
A10: ULC-QA-008 | B10: 移动或窄屏后台适配 | C10: P5 | D10: V1.0 | E10: 使用窄屏分辨率或浏览器响应式模式 | F10: 1. 将窗口缩小到常见窄屏宽度 2. 查看列表横向滚动、操作列和弹窗 3. 执行编辑保存 | G10: 表格可横向滚动或自适应；关键操作不被遮挡；弹窗按钮可见；不出现布局错乱导致无法保存 | H10: 有响应式断点、操作列可见； | I10: PASS
A11: ULC-QA-009 | B11: 核心回归链路 | C11: P2 | D11: V1.0 | E11: 版本发版前回归环境可用 | F11: 1. 回归查看列表 2. 回归新增/编辑合法配置 3. 回归阈值调低升级、调高降级 4. 回归权益折扣和免押金 5. 回归权限拦截 | G11: 核心链路均通过；资金/权益计算无回归缺陷；权限拦截和Lv.1保护仍生效；审计日志完整 | H11: 列表6条记录、表单校验完整、权益字段齐全、Lv.1保护生效 | I11: PASS
