Workbook

Sheet 用例统计
A1: 前台秒杀专区与无货秒赔专区 - 测试用例统计
A3: 优先级定义标准:
A4: P1(阻断级) | B4: 核心主流程不可用/资金安全风险/数据丢失。发版前必须100%通过
A5: P2(核心功能) | B5: 主要功能正确性问题，有临时绕过方案。发版前必须通过
A6: P3(重要功能) | B6: 非核心功能异常或边界处理不当。发版前应通过
A7: P4(一般功能) | B7: UI展示问题/文案错误/非关键交互异常。发版后修复
A8: P5(优化建议) | B8: 性能优化/样式微调/兼容性/无障碍。迭代优化
A11: 模块 | B11: 端类型 | C11: 用例数 | D11: P1 | E11: P2 | F11: P3 | G11: P4 | H11: P5
A12: 秒杀专区-入口与页面展示 | B12: H5端 | C12: =COUNTA('秒杀专区-入口与页面展示'!A3:A200) -> 8 | D12: =COUNTIF('秒杀专区-入口与页面展示'!C3:C200,"P1") -> 0 | E12: =COUNTIF('秒杀专区-入口与页面展示'!C3:C200,"P2") -> 2 | F12: =COUNTIF('秒杀专区-入口与页面展示'!C3:C200,"P3") -> 5 | G12: =COUNTIF('秒杀专区-入口与页面展示'!C3:C200,"P4") -> 1 | H12: =COUNTIF('秒杀专区-入口与页面展示'!C3:C200,"P5") -> 0
A13: 秒杀专区-商品列表与活动时间 | B13: H5端 | C13: =COUNTA('秒杀专区-商品列表与活动时间'!A3:A199) -> 7 | D13: =COUNTIF('秒杀专区-商品列表与活动时间'!C3:C199,"P1") -> 1 | E13: =COUNTIF('秒杀专区-商品列表与活动时间'!C3:C199,"P2") -> 3 | F13: =COUNTIF('秒杀专区-商品列表与活动时间'!C3:C199,"P3") -> 2 | G13: =COUNTIF('秒杀专区-商品列表与活动时间'!C3:C199,"P4") -> 1 | H13: =COUNTIF('秒杀专区-商品列表与活动时间'!C3:C199,"P5") -> 0
A14: 秒杀专区-下单与状态流转 | B14: H5端 | C14: =COUNTA('秒杀专区-下单与状态流转'!A3:A197) -> 5 | D14: =COUNTIF('秒杀专区-下单与状态流转'!C3:C197,"P1") -> 3 | E14: =COUNTIF('秒杀专区-下单与状态流转'!C3:C197,"P2") -> 2 | F14: =COUNTIF('秒杀专区-下单与状态流转'!C3:C197,"P3") -> 0 | G14: =COUNTIF('秒杀专区-下单与状态流转'!C3:C197,"P4") -> 0 | H14: =COUNTIF('秒杀专区-下单与状态流转'!C3:C197,"P5") -> 0
A15: 秒杀专区-异常与边界处理 | B15: H5端 | C15: =COUNTA('秒杀专区-异常与边界处理'!A3:A200) -> 6 | D15: =COUNTIF('秒杀专区-异常与边界处理'!C3:C200,"P1") -> 1 | E15: =COUNTIF('秒杀专区-异常与边界处理'!C3:C200,"P2") -> 4 | F15: =COUNTIF('秒杀专区-异常与边界处理'!C3:C200,"P3") -> 1 | G15: =COUNTIF('秒杀专区-异常与边界处理'!C3:C200,"P4") -> 0 | H15: =COUNTIF('秒杀专区-异常与边界处理'!C3:C200,"P5") -> 0
A16: 无货秒赔-入口与规则展示 | B16: H5端 | C16: =COUNTA('无货秒赔-入口与规则展示'!A3:A200) -> 7 | D16: =COUNTIF('无货秒赔-入口与规则展示'!C3:C200,"P1") -> 0 | E16: =COUNTIF('无货秒赔-入口与规则展示'!C3:C200,"P2") -> 3 | F16: =COUNTIF('无货秒赔-入口与规则展示'!C3:C200,"P3") -> 2 | G16: =COUNTIF('无货秒赔-入口与规则展示'!C3:C200,"P4") -> 2 | H16: =COUNTIF('无货秒赔-入口与规则展示'!C3:C200,"P5") -> 0
A17: 无货秒赔-异常与边界处理 | B17: H5端 | C17: =COUNTA('无货秒赔-异常与边界处理'!A3:A200) -> 6 | D17: =COUNTIF('无货秒赔-异常与边界处理'!C3:C200,"P1") -> 0 | E17: =COUNTIF('无货秒赔-异常与边界处理'!C3:C200,"P2") -> 3 | F17: =COUNTIF('无货秒赔-异常与边界处理'!C3:C200,"P3") -> 3 | G17: =COUNTIF('无货秒赔-异常与边界处理'!C3:C200,"P4") -> 0 | H17: =COUNTIF('无货秒赔-异常与边界处理'!C3:C200,"P5") -> 0
A18: 合计 | C18: =SUM(C12:C17) -> 39 | D18: =SUM(D12:D17) -> 5 | E18: =SUM(E12:E17) -> 17 | F18: =SUM(F12:F17) -> 13 | G18: =SUM(G12:G17) -> 4 | H18: =SUM(H12:H17) -> 0
A20: P1占比: | B20: =CONCATENATE("P1占比 ",TEXT(D18/C18,"0.0%")," (",D18,"/",C18,")") -> P1占比 12.8% (5/39)

Sheet 秒杀专区-入口与页面展示
A1: 前台秒杀与无货秒赔 - 秒杀专区 - 入口与页面展示
A2: 用例编号 | B2: 测试项 | C2: 优先级 | D2: 端类型 | E2: 归属版本 | F2: 前置条件 | G2: 输入/执行步骤 | H2: 预计结果 | I2: 实际结果 | J2: 是否通过
A3: SK-EN-001 | B3: H5首页秒杀专区入口位置展示 | C3: P2 | D3: H5端 | E3: V1.0 | F3: H5端首页已加载完成，存在进行中的秒杀活动 | G3: 1. 用户打开H5端首页 2. 查看秒杀专区入口位置 3. 核对入口是否在首页显著位置 4. 查看入口展示样式(图标+文案) | H3: H5端首页展示秒杀专区入口；入口位于首页显著位置(如banner下方或导航栏)；入口包含图标和「秒杀专区」文案；入口样式与整体UI风格一致 | I3: 展示正确 | J3: PASS
A4: SK-EN-002 | B4: 秒杀入口图标和文案展示 | C4: P4 | D4: H5端 | E4: V1.0 | F4: H5端首页已加载 | G4: 1. 查看秒杀入口图标是否加载正常 2. 查看文案内容 3. 在不同屏幕尺寸下查看入口展示 4. 查看入口是否有动效(如闪烁/跳动) | H4: 秒杀入口图标加载正常无裂图；文案为「秒杀专区」或类似；不同屏幕尺寸下入口展示正常不错位；有动效吸引注意(如进行中时闪烁) | I4: 展示正常 | J4: PASS
A5: SK-EN-003 | B5: 未登录用户秒杀入口可见性 | C5: P3 | D5: H5端 | E5: V1.0 | F5: 用户未登录，打开H5端首页 | G5: 1. 未登录状态下查看首页秒杀入口 2. 点击秒杀入口 3. 查看跳转后的页面 4. 查看是否引导登录 | H5: 未登录用户首页可见秒杀入口；点击入口跳转至秒杀专区页面；秒杀专区页面可浏览商品；下单时引导用户登录 | I5: 未登录用户对页面可见；但是商品详细信息必须要登录注册 | J5: PASS
A6: SK-EN-004 | B6: 活动未开始时入口展示状态 | C6: P3 | D6: H5端 | E6: V1.0 | F6: 存在未开始的秒杀活动，无进行中活动 | G6: 1. 查看首页秒杀入口状态 2. 查看入口是否有「即将开始」标识 3. 查看入口是否展示开始时间 4. 点击入口查看专区页面 | H6: 活动未开始时入口仍展示；入口有「即将开始」或开始时间标识；点击入口可进入专区查看预告商品；专区页面展示「距开始XX:XX:XX」倒计时 | I6: 可查看立即秒杀时间（倒计时可见），并且显示减少的价格 | J6: PASS
A7: SK-EN-005 | B7: 活动进行中入口高亮动效 | C7: P3 | D7: H5端 | E7: V1.0 | F7: 存在进行中的秒杀活动 | G7: 1. 查看首页秒杀入口状态 2. 查看入口是否有高亮/动效 3. 查看是否有「进行中」或「火热进行」标识 4. 点击入口进入专区 | H7: 活动进行中入口有高亮或动效；入口展示「进行中」或「火热抢购」标识；点击入口快速进入秒杀专区；专区页面默认展示进行中的商品 | I7: 展示正常 | J7: PASS
A8: SK-EN-006 | B8: 活动已结束入口隐藏或置灰 | C8: P3 | D8: H5端 | E8: V1.0 | F8: 所有秒杀活动均已结束，无进行中和未开始的活动 | G8: 1. 查看首页是否有秒杀入口 2. 若入口存在查看是否置灰 3. 点击入口查看跳转 4. 查看专区页面展示 | H8: 活动全部结束时入口隐藏或置灰展示；若入口置灰点击提示「暂无秒杀活动」；专区页面展示空状态或「暂无进行中的秒杀活动」 | I8: 功能正常，跳转进入秒杀页面 | J8: PASS
A9: SK-EN-007 | B9: 点击秒杀入口跳转专区页面 | C9: P2 | D9: H5端 | E9: V1.0 | F9: 存在进行中的秒杀活动 | G9: 1. 点击首页秒杀入口 2. 查看页面跳转 3. 查看跳转URL 4. 查看页面加载速度 5. 查看返回是否可回到首页 | H9: 点击入口成功跳转至秒杀专区页面；跳转URL正确；页面加载时间≤2秒；可通过返回按钮回到首页；跳转过程无白屏或闪烁 | I9: 页面加载正常；页面加载<=1s跳转无白屏或者闪烁； | J9: PASS
A10: SK-EN-008 | B10: 秒杀专区页面加载与空状态 | C10: P3 | D10: H5端 | E10: V1.0 | F10: 秒杀专区无任何商品或活动数据 | G10: 1. 进入秒杀专区页面 2. 查看页面加载状态 3. 查看空状态展示 4. 查看是否有引导文案 5. 下拉刷新查看 | H10: 专区页面正常加载无报错；无商品时展示空状态插画和文案；空状态文案友好(如「暂无秒杀商品，敬请期待」)；下拉刷新可重新加载；无商品时无报错弹窗 | I10: 展示口状态插画以及提示暂无数据 | J10: PASS

Sheet 秒杀专区-商品列表与活动时间
A1: 前台秒杀与无货秒赔 - 秒杀专区 - 商品列表与活动时间
A2: 用例编号 | B2: 测试项 | C2: 优先级 | D2: 端类型 | E2: 归属版本 | F2: 前置条件 | G2: 输入/执行步骤 | H2: 预计结果 | I2: 实际结果 | J2: 是否通过
A3: SK-PL-001 | B3: 秒杀商品列表加载与展示 | C3: P2 | D3: H5端 | E3: V1.0 | F3: 秒杀专区有多个进行中的秒杀商品 | G3: 1. 进入秒杀专区页面 2. 查看商品列表加载 3. 核对商品数量与后台一致 4. 查看列表布局(单列/双列) | H3: 商品列表正常加载；展示的商品数量与后台配置一致；列表布局合理(单列或双列)；商品按场次或开始时间排序；列表加载时间≤2秒 | I3: 单列正常排布，插在实际<=2s | J3: PASS
A4: SK-PL-002 | B4: 商品图片名称秒杀价原价展示 | C4: P2 | D4: H5端 | E4: V1.0 | F4: 秒杀专区有进行中的商品 | G4: 1. 查看秒杀商品卡片信息 2. 核对商品图片 3. 核对商品名称 4. 核对秒杀价和原价 5. 核对折扣力度展示 | H4: 商品图片清晰加载无变形；商品名称完整展示(超长截断或换行)；秒杀价突出展示(红色/大字号)；原价划线展示；折扣力度(如5折)清晰可见 | I4: 展示正常；原价划线显示秒杀价 | J4: PASS
A5: SK-PL-004 | B5: 秒杀倒计时展示与实时更新 | C5: P1 | D5: H5端 | E5: V1.0 | F5: 秒杀活动进行中，距结束还有1小时 | G5: 1. 查看秒杀商品倒计时展示 2. 核对倒计时时间准确性 3. 等待1分钟查看倒计时是否更新 4. 倒计时归零时查看状态变化 | H5: 倒计时展示格式为HH:MM:SS或XX分XX秒；倒计时时间与服务器时间一致；倒计时每秒自动更新；倒计时归零后商品状态变为已结束或已售罄 | I5: 秒杀倒计时实时变化 | J5: PASS
A6: SK-PL-005 | B6: 已售罄商品状态展示 | C6: P3 | D6: H5端 | E6: V1.0 | F6: 秒杀商品库存为0 | G6: 1. 查看已售罄商品卡片 2. 查看是否有「已抢光」标识 3. 查看按钮状态 4. 点击已售罄商品查看 | H6: 已售罄商品卡片展示「已抢光」或「已售罄」标识；抢购按钮置灰不可点击；商品图片可能添加售罄水印；点击商品可查看详情但无法下单 | I6: 展示口状态插画以及提示暂无数据 | J6: PASS
A7: SK-PL-006 | B7: 多场次秒杀切换 | C7: P2 | D7: H5端 | E7: V1.0 | F7: 存在多个秒杀场次(如10点场、14点场、20点场) | G7: 1. 查看多场次tab展示 2. 点击未开始场次查看 3. 点击进行中场次查看 4. 点击已结束场次查看 5. 核对各场次商品列表 | H7: 多场次以tab或列表形式展示；未开始场次展示开始时间和预告商品；进行中场次高亮并展示可抢购商品；已结束场次展示已售罄状态；切换场次商品列表正确切换 | I7: 未设置分段秒杀时间 | J7: TWD
A8: SK-PL-007 | B8: 秒杀商品筛选与排序 | C8: P3 | D8: H5端 | E8: V1.0 | F8: 秒杀专区有多个不同类型的商品 | G8: 1. 查看是否有筛选功能 2. 按商品类型筛选(如游戏/社交) 3. 按价格排序(从低到高) 4. 按折扣力度排序 5. 查看筛选结果 | H8: 专区支持按商品类型筛选；支持按价格/折扣排序；筛选和排序结果正确；筛选后无数据时展示空状态；筛选条件可清除重置 | I8: 多种筛选功能，筛选后无结果显示’暂无数据‘；可以一键清空重置 | J8: PASS
A9: SK-PL-008 | B9: 商品列表分页与滚动加载 | C9: P4 | D9: H5端 | E9: V1.0 | F9: 秒杀商品数量超过一屏 | G9: 1. 滚动查看商品列表 2. 查看是否自动加载更多 3. 查看分页加载性能 4. 快速滚动查看是否有白屏 5. 滚动到底部查看 | H9: 商品列表支持滚动加载或分页；滚动到底部自动加载下一页；加载过程有loading提示；快速滚动无白屏或卡顿；无更多数据时展示「没有更多了」 | I9: 滚动页面自动加载商品，快速滚动显示在加载中 | J9: PASS

Sheet 秒杀专区-下单与状态流转
A1: 前台秒杀与无货秒赔 - 秒杀专区 - 下单与库存控制
A2: 用例编号 | B2: 测试项 | C2: 优先级 | D2: 端类型 | E2: 归属版本 | F2: 前置条件 | G2: 输入/执行步骤 | H2: 预计结果 | I2: 实际结果 | J2: 是否通过
A3: SK-OD-001 | B3: 秒杀商品下单流程 | C3: P1 | D3: H5端 | E3: V1.0 | F3: 用户已登录，秒杀商品有库存且活动进行中 | G3: 1. 点击秒杀商品进入详情/直接点击抢购 2. 选择租赁期限 3. 确认订单信息 4. 提交订单 5. 查看订单结果 | H3: 点击抢购进入下单流程；可选择租赁期限；订单信息展示秒杀价和原价对比；提交订单成功并生成订单号；跳转至支付页面或订单详情 | I3: 功能流转正常 | J3: PASS
A4: SK-OD-002 | B4: 秒杀库存实时扣减 | C4: P1 | D4: H5端 | E4: V1.0 | F4: 秒杀商品剩余库存为5件 | G4: 1. 用户A下单抢购1件 2. 查看库存是否变为4件 3. 用户B同时下单抢购1件 4. 查看库存是否变为3件 5. 查看进度条更新 | H4: 下单成功后库存实时扣减；扣减后列表和详情页库存同步更新；进度条同步更新；库存为0时自动变为售罄状态；库存扣减与订单生成原子性保证 | I4: 下单数据实时同步，下单以先付款的为准 | J4: PASS
A5: SK-OD-003 | B5: 单用户限购规则校验 | C5: P2 | D5: H5端 | E5: V1.0 | F5: 系统未用户对秒杀数量进行限制 | G5: 1. 用户已抢购1件后再次进入秒杀专区 2. 查看该商品抢购按钮状态 3. 尝试再次下单 4. 查看是否有提示 | H5: 无提示，用户可以随意购买；下单成功后订单在秒杀页面消失 | I5: 无提示，用户可以随意购买；下单成功后订单在秒杀页面消失 | J5: PASS
A6: SK-OD-004 | B6: 秒杀成功订单生成 | C6: P1 | D6: H5端 | E6: V1.0 | F6: 用户已登录，秒杀商品有库存 | G6: 1. 用户提交秒杀订单 2. 查看订单是否生成 3. 核对订单金额(秒杀价) 4. 核对订单商品信息 5. 查看订单状态 | H6: 秒杀成功后订单正常生成；订单金额为秒杀价而非原价；订单商品信息与秒杀商品一致；订单状态为待支付或已确认；订单关联秒杀活动ID | I6: 秒杀成功后订单正常生成；订单金额为秒杀价而非原价；订单商品信息与秒杀商品一致；订单状态变为为待支付或已确认；订单关联秒杀活动ID | J6: PASS
A7: SK-OD-005 | B7: 秒杀成功页面跳转与提示 | C7: P2 | D7: H5端 | E7: V1.0 | F7: 用户已成功提交秒杀订单 | G7: 1. 提交订单成功后查看页面 2. 查看是否有成功提示 3. 查看页面跳转 4. 查看订单详情入口 5. 查看支付倒计时 | H7: 下单成功后展示成功提示(如「抢购成功」)；页面跳转至订单详情或支付页；有查看订单详情入口；若有支付时限则展示支付倒计时；成功提示展示2-3秒后自动跳转 | I7: 点击秒杀按钮，跳转到支付页面，显示支付时效 | J7: PASS

Sheet 秒杀专区-异常与边界处理
A1: 前台秒杀与无货秒赔 - 秒杀专区 - 异常与边界处理
A2: 用例编号 | B2: 测试项 | C2: 优先级 | D2: 端类型 | E2: 归属版本 | F2: 前置条件 | G2: 输入/执行步骤 | H2: 预计结果 | I2: 实际结果 | J2: 是否通过
A3: SK-EX-001 | B3: 并发秒杀库存防超卖 | C3: P1 | D3: H5端 | E3: V1.0 | F3: 秒杀商品剩余库存为1件，多个用户同时抢购 | G3: 1. 构造10个用户同时下单抢购最后1件库存 2. 查看最终成功下单数量 3. 查看库存是否变为0 4. 查看其他9个用户的下单结果 5. 查看是否有重复扣减 | H3: 仅1个用户成功下单；库存正确扣减为0；其余9个用户下单失败提示「已抢光」；无超卖现象(成功数≤库存数)；后端使用分布式锁或原子操作保证 | I3: 只成功一个用户，第一个成功付款的用户未准 | J3: PASS
A4: SK-EX-002 | B4: 网络异常下单重试 | C4: P2 | D4: H5端 | E4: V1.0 | F4: 用户秒杀下单时网络不稳定 | G4: 1. 用户点击抢购时断开网络 2. 查看页面提示 3. 恢复网络后查看 4. 查看是否需要重新提交 5. 查看订单状态 | H4: 网络断开时提示「网络异常请重试」；恢复网络后可重新提交；不生成重复订单；若已提交成功则提示「已抢购成功」；订单状态与实际一致 | I4: 显示网络请求失败，请重试，网络恢复后可出现提交 | J4: PASS
A5: SK-EX-003 | B5: 重复点击下单防抖 | C5: P2 | D5: H5端 | E5: V1.0 | F5: 用户快速多次点击抢购按钮 | G5: 1. 用户快速连续点击抢购按钮5次 2. 查看是否只提交一次请求 3. 查看按钮状态变化 4. 查看订单生成数量 5. 查看接口调用次数 | H5: 快速连续点击仅提交一次请求；点击后按钮置灰或显示loading；不生成多个订单；接口仅调用一次；防抖时间≥1秒 | I5: 连续点击只会提交异常，并且提示请勿重复点击；接口只调用一次 | J5: PASS
A6: SK-EX-004 | B6: 秒杀下单超时处理 | C6: P2 | D6: H5端 | E6: V1.0 | F6: 秒杀下单请求超时(后端响应超过10秒) | G6: 1. 模拟下单请求超时 2. 查看页面loading状态 3. 查看超时后提示 4. 查看是否自动重试 5. 查看库存是否已扣减 | H6: 下单请求超时后页面提示「请求超时请重试」；loading状态自动消失；不自动重试(需用户手动)；后端已扣减库存则提示「已抢购成功」；未扣减则可重新下单 | I6: 页面提示请求超时，请重新下单 | J6: PASS
A7: SK-EX-005 | B7: 库存为0时按钮状态 | C7: P3 | D7: H5端 | E7: V1.0 | F7: 秒杀商品库存刚好为0 | G7: 1. 查看库存为0时按钮状态 2. 查看按钮文案 3. 查看按钮是否可点击 4. 查看商品卡片是否有售罄标识 5. 查看进度条是否满格 | H7: 库存为0时按钮置灰不可点击；按钮文案变为「已抢光」；商品卡片有售罄标识；进度条满格展示100%；状态实时更新无延迟 | I7: 秒杀专区消失 | J7: FAIL
A8: SK-EX-006 | B8: 秒杀活动结束瞬间下单处理 | C8: P2 | D8: H5端 | E8: V1.0 | F8: 用户在秒杀活动即将结束(剩余1秒)时下单 | G8: 1. 用户在活动结束前1秒点击抢购 2. 查看请求到达后端时活动是否已结束 3. 查看下单结果 4. 查看库存是否扣减 5. 查看提示信息 | H8: 若请求到达时活动已结束则下单失败；提示「活动已结束」；不扣减库存；若请求到达时活动未结束则正常下单；后端以服务器时间为准判断 | I8: 以下单时间为准，下单之前结束，提示下单失败；下单完成只会结束，无影响 | J8: PASS

Sheet 无货秒赔-入口与规则展示
A1: 前台秒杀与无货秒赔 - 无货秒赔 - 入口与规则展示
A2: 用例编号 | B2: 测试项 | C2: 优先级 | D2: 端类型 | E2: 归属版本 | F2: 前置条件 | G2: 输入/执行步骤 | H2: 预计结果 | I2: 实际结果 | J2: 是否通过
A3: CP-EN-001 | B3: H5首页无货秒赔入口展示 | C3: P2 | D3: H5端 | E3: V1.0 | F3: H5端首页已加载，无货秒赔功能已上线 | G3: 1. 用户打开H5端首页 2. 查看无货秒赔入口位置 3. 核对入口图标和文案 4. 查看入口与秒杀入口的区分 | H3: H5端首页展示无货秒赔专区入口；入口位置合理(如秒杀入口附近或服务保障区域)；入口包含图标和「无货秒赔」文案；与秒杀专区入口有明确区分(不同图标/颜色) | I3: 展示正常 | J3: PASS
A4: CP-EN-002 | B4: 无货秒赔入口图标和文案展示 | C4: P4 | D4: H5端 | E4: V1.0 | F4: H5端首页已加载 | G4: 1. 查看入口图标是否正常加载 2. 查看文案内容 3. 查看入口样式 4. 在不同屏幕尺寸下查看 | H4: 入口图标加载正常无裂图；文案为「无货秒赔」或「无货赔付」；入口样式与整体UI一致；不同屏幕尺寸下展示正常 | I4: 展示正常 | J4: PASS
A5: CP-EN-003 | B5: 点击无货秒赔入口跳转专区 | C5: P2 | D5: H5端 | E5: V1.0 | F5: 无货秒赔功能已上线 | G5: 1. 点击首页无货秒赔入口 2. 查看页面跳转 3. 查看跳转URL 4. 查看页面加载速度 5. 查看返回操作 | H5: 点击入口成功跳转至无货秒赔专区页面；跳转URL正确；页面加载时间≤2秒；可通过返回按钮回到首页；跳转无白屏 | I5: 功能正常，跳转时间<=2s，可通过返回按钮返回首页 | J5: PASS
A6: CP-EN-004 | B6: 无货秒赔规则说明展示 | C6: P2 | D6: H5端 | E6: V1.0 | F6: 无货秒赔专区页面已加载 | G6: 1. 查看专区页面规则说明区域 2. 核对秒赔规则文案 3. 查看适用条件 4. 查看赔付标准 5. 查看是否有FAQ | H6: 专区页面展示秒赔规则说明；规则文案清晰易懂；展示适用条件(如无货定义、申请时限)；展示赔付标准(如全额退款+额外赔付)；有常见问题FAQ | I6: 展示正常 | J6: PASS
A7: CP-EN-005 | B7: 无货秒赔商品列表展示 | C7: P3 | D7: H5端 | E7: V1.0 | F7: 无货秒赔专区有可申请秒赔的商品 | G7: 1. 查看秒赔商品列表 2. 核对商品信息展示 3. 查看商品状态标识 4. 查看申请按钮 5. 查看列表排序 | H7: 专区展示可申请秒赔的商品列表；商品信息包含图片/名称/租赁信息；商品状态标识清晰(如「无货」「可申请秒赔」)；每条商品有「申请秒赔」按钮；列表按时间或状态排序 | I7: 展示正常 | J7: PASS
A8: CP-EN-006 | B8: 无货秒赔专区空状态展示 | C8: P4 | D8: H5端 | E8: V1.0 | F8: 用户无符合秒赔条件的订单 | G8: 1. 进入无货秒赔专区 2. 查看空状态展示 3. 查看引导文案 4. 查看是否有客服入口 5. 查看刷新功能 | H8: 无符合条件商品时展示空状态；空状态文案友好(如「暂无需要秒赔的订单」)；有引导文案说明秒赔条件；空状态页面有客服咨询入口；支持下拉刷新 | I8: 展示正常 | J8: PASS
A9: CP-EN-007 | B9: 秒赔入口与秒杀入口区分 | C9: P3 | D9: H5端 | E9: V1.0 | F9: H5端首页同时展示秒杀专区和无货秒赔专区入口 | G9: 1. 查看两个入口的位置关系 2. 核对图标差异 3. 核对文案差异 4. 核对颜色/样式差异 5. 分别点击确认跳转正确 | H9: 两个入口位置相近但有明确区分；图标不同(秒杀vs秒赔)；文案不同(「秒杀专区」vs「无货秒赔」)；颜色或样式有区分；点击各自跳转至正确页面 | I9: 有明确区分；图标文案不同；颜色样式分辨清楚 | J9: PASS

Sheet 无货秒赔-异常与边界处理
A1: 前台秒杀与无货秒赔 - 无货秒赔 - 异常与边界处理
A2: 用例编号 | B2: 测试项 | C2: 优先级 | D2: 端类型 | E2: 归属版本 | F2: 前置条件 | G2: 输入/执行步骤 | H2: 预计结果 | I2: 实际结果 | J2: 是否通过
A3: CP-EX-001 | B3: 重复申请秒赔拦截 | C3: P2 | D3: H5端 | E3: V1.0 | F3: 用户已对某无货订单提交秒赔申请 | G3: 1. 用户对同一订单再次申请秒赔 2. 查看是否被拦截 3. 查看提示信息 4. 通过接口重复提交 5. 查看申请记录 | H3: 同一订单重复申请被前端拦截；提示「该订单已提交秒赔申请」；通过接口重复提交被后端拦截；每个订单仅允许一次秒赔申请；申请记录无重复 | I3: 提示「该订单已提交秒赔申请」；并且通过接口重复提交被后端拦截 | J3: PASS
A4: CP-EX-002 | B4: 非无货商品申请秒赔拦截 | C4: P2 | D4: H5端 | E4: V1.0 | F4: 用户订单商品状态为正常发货，非无货状态 | G4: 1. 查看正常订单是否显示秒赔入口 2. 尝试通过URL直接访问申请页 3. 通过接口提交秒赔申请 4. 查看拦截提示 5. 查看订单状态判断逻辑 | H4: 正常发货订单不展示秒赔申请入口；通过URL访问申请页展示「该订单不符合秒赔条件」；接口提交被后端状态校验拦截；拦截提示清晰；后端以订单实际状态为准 | I4: 以后台订单状态为准 | J4: PASS
A5: CP-EX-003 | B5: 秒赔申请次数限制 | C5: P3 | D5: H5端 | E5: V1.0 | F5: 用户有多个无货订单，尝试全部申请秒赔 | G5: 1. 查看用户可申请秒赔的订单数量 2. 逐一提交秒赔申请 3. 查看是否有次数限制 4. 查看申请记录数量 5. 查看是否有限制提示 | H5: 用户可对多个不同无货订单分别申请秒赔；每个订单独立申请互不影响；申请记录完整展示；若有次数限制则提示「本月已达秒赔申请上限」；无限制时全部可申请 | I5: 每个订单独立的，用户可以对多个订单进行申请 | J5: PASS
A6: CP-EX-004 | B6: 秒赔到账失败重试 | C6: P2 | D6: H5端 | E6: V1.0 | F6: 秒赔审核通过但赔付到账失败(如余额系统异常) | G6: 1. 查看到账失败状态 2. 查看失败原因 3. 查看是否自动重试 4. 查看重试次数和间隔 5. 查看最终到账结果 | H6: 到账失败后状态标识为「到账失败」；展示失败原因(如系统繁忙)；系统自动重试(间隔5分钟/30分钟/2小时)；重试3次仍失败则转人工处理；最终到账后状态更新为「已到账」 | I6: 到账失败不在用户端显示问题，系统自动重试，到账了才会显示【已到账】 | J6: PASS
A7: CP-EX-005 | B7: 秒赔记录历史查询 | C7: P3 | D7: H5端 | E7: V1.0 | F7: 用户有多条历史秒赔申请记录 | G7: 1. 进入秒赔记录页面 2. 查看历史记录列表 3. 按状态筛选(全部/通过/驳回) 4. 按时间排序 5. 查看记录详情 | H7: 账单记录页面展示所有历史申请；列表包含申请编号/订单号/申请时间/状态/金额；支持按状态筛选；支持按时间排序(最新优先)；点击记录可查看详情 | I7: 账单记录页面展示所有历史申请；列表包含申请编号/订单号/申请时间/状态/金额；按状态筛选；按时间排序(最新优先)；点击记录可查看详情 | J7: PASS
A8: CP-EX-006 | B8: 客服介入秒赔流程 | C8: P3 | D8: H5端 | E8: V1.0 | F8: 用户对秒赔审核结果有异议 | G8: 1. 用户在秒赔记录页点击「联系客服」 2. 查看客服咨询入口 3. 提交问题描述 4. 查看客服回复 5. 查看客服处理结果 | H8: 秒赔记录页有「联系客服」入口；可跳转至在线客服或提交工单；客服可查看秒赔申请详情；客服处理后结果同步至秒赔记录；客服介入有记录可追溯 | I8: 客服可查看用户信息/订单信息/商品信息/个独立判断用户问题 | J8: PASS
